Workbook
Name Slicer_Category: #N/A
Name Slicer_Stock_Status: #N/A
Name Slicer_Weight_Category: #N/A
Name Slicer_Discount_Band: #N/A

Sheet Zepto Slicer Dashboard
B1: Zepto Inventory - Pivot & Slicer Dashboard
B2: Click the slicers on the left (Ctrl+click for multi-select). Every pivot table and chart on this page updates. Built on real PivotTables.

Sheet Zepto Dashboard
B1: Zepto Inventory - Interactive Dashboard
B2: Pick a Group by, Value field, Aggregation, Split and filters in the yellow cells - every chart and KPI updates. Source: Zepto_v1__1_.csv (cleaned as in your SQL).
B4: CONTROLS | F4: SKUs (FILTERED) | I4: OUT-OF-STOCK SHARE | L4: AVERAGE DISCOUNT % | O4: ESTIMATED REVENUE (Rs)
B5: Group by (X axis) | C5: Category | F5: =COUNTIFS(Zepto_Data!$A$2:$A$3732,ZP_Engine!$B$11,Zepto_Data!$L$2:$L$3732,ZP_Engine!$B$12,Zepto_Data!$K$2:$K$3732,ZP_Engine!$B$13,Zepto_Data!$M$2:$M$3732,ZP_Engine!$B$14) -> 3731 | I5: =IFERROR(COUNTIFS(Zepto_Data!$L$2:$L$3732,"Out of stock",Zepto_Data!$A$2:$A$3732,ZP_Engine!$B$11,Zepto_Data!$L$2:$L$3732,ZP_Engine!$B$12,Zepto_Data!$K$2:$K$3732,ZP_Engine!$B$13,Zepto_Data!$M$2:$M$3732,ZP_Engine!$B$14)/COUNTIFS(Zepto_Data!$A$2:$A$3732,ZP_Engine!$B$11,Zepto_Data!$L$2:$L$3732,ZP_Engine!$B$12,Zepto_Data!$K$2:$K$3732,ZP_Engine!$B$13,Zepto_Data!$M$2:$M$3732,ZP_Engine!$B$14),0) -> 0.12141517 | L5: =IFERROR(AVERAGEIFS(Zepto_Data!$D$2:$D$3732,Zepto_Data!$A$2:$A$3732,ZP_Engine!$B$11,Zepto_Data!$L$2:$L$3732,ZP_Engine!$B$12,Zepto_Data!$K$2:$K$3732,ZP_Engine!$B$13,Zepto_Data!$M$2:$M$3732,ZP_Engine!$B$14),0) -> 7.619137 | O5: =SUMIFS(Zepto_Data!$J$2:$J$3732,Zepto_Data!$A$2:$A$3732,ZP_Engine!$B$11,Zepto_Data!$L$2:$L$3732,ZP_Engine!$B$12,Zepto_Data!$K$2:$K$3732,ZP_Engine!$B$13,Zepto_Data!$M$2:$M$3732,ZP_Engine!$B$14) -> 2243080.6
B6: Value field (Y axis) | C6: Revenue (Rs)
B7: Aggregation | C7: Sum | F7: =IF('Zepto Dashboard'!$C$7="Count","Count of records",'Zepto Dashboard'!$C$7&" of "&'Zepto Dashboard'!$C$6)&" by "&'Zepto Dashboard'!$C$5 -> Sum of Revenue (Rs) by Category | O7: ="Split: "&IF('Zepto Dashboard'!$C$7="Count","Count of records",'Zepto Dashboard'!$C$7&" of "&'Zepto Dashboard'!$C$6)&" by "&'Zepto Dashboard'!$C$5&IF('Zepto Dashboard'!$C$8="None",""," and "&'Zepto Dashboard'!$C$8) -> Split: Sum of Revenue (Rs) by Category
B8: Split by (legend) | C8: None
B9: Sort | C9: Value: high to low
B10: Show top N | C10: 12
B11: FILTERS
B12: Category | C12: All
B13: Stock status | C13: All
B14: Weight category | C14: All
B15: Discount band | C15: All
B19: TOP-N BREAKDOWN (current selection)
B20: Item | C20: Value | D20: Share
B21: =IF(ZP_Engine!C45="","",ZP_Engine!C45) -> Cooking Essentials | C21: =IF(ZP_Engine!C45="","",ZP_Engine!D45) -> 337369 | D21: =IF(ZP_Engine!E45="","",ZP_Engine!E45) -> 0.15040431
B22: =IF(ZP_Engine!C46="","",ZP_Engine!C46) -> Munchies | C22: =IF(ZP_Engine!C46="","",ZP_Engine!D46) -> 337369 | D22: =IF(ZP_Engine!E46="","",ZP_Engine!E46) -> 0.15040431
B23: =IF(ZP_Engine!C47="","",ZP_Engine!C47) -> Paan Corner | C23: =IF(ZP_Engine!C47="","",ZP_Engine!D47) -> 270849 | D23: =IF(ZP_Engine!E47="","",ZP_Engine!E47) -> 0.12074867
B24: =IF(ZP_Engine!C48="","",ZP_Engine!C48) -> Personal Care | C24: =IF(ZP_Engine!C48="","",ZP_Engine!D48) -> 270849 | D24: =IF(ZP_Engine!E48="","",ZP_Engine!E48) -> 0.12074867
B25: =IF(ZP_Engine!C49="","",ZP_Engine!C49) -> Chocolates & Candies | C25: =IF(ZP_Engine!C49="","",ZP_Engine!D49) -> 224385 | D25: =IF(ZP_Engine!E49="","",ZP_Engine!E49) -> 0.1000343 | F25: ="Share of "&'Zepto Dashboard'!$C$6&" by "&'Zepto Dashboard'!$C$5&" (top N)" -> Share of Revenue (Rs) by Category (top N) | O25: ="SKUs: in stock vs out of stock (filters applied)" -> SKUs: in stock vs out of stock (filters applied)
B26: =IF(ZP_Engine!C50="","",ZP_Engine!C50) -> Ice Cream & Desserts | C26: =IF(ZP_Engine!C50="","",ZP_Engine!D50) -> 224385 | D26: =IF(ZP_Engine!E50="","",ZP_Engine!E50) -> 0.1000343
B27: =IF(ZP_Engine!C51="","",ZP_Engine!C51) -> Packaged Food | C27: =IF(ZP_Engine!C51="","",ZP_Engine!D51) -> 224385 | D27: =IF(ZP_Engine!E51="","",ZP_Engine!E51) -> 0.1000343
B28: =IF(ZP_Engine!C52="","",ZP_Engine!C52) -> Home & Cleaning | C28: =IF(ZP_Engine!C52="","",ZP_Engine!D52) -> 122661 | D28: =IF(ZP_Engine!E52="","",ZP_Engine!E52) -> 0.05468417
B29: =IF(ZP_Engine!C53="","",ZP_Engine!C53) -> Health & Hygiene | C29: =IF(ZP_Engine!C53="","",ZP_Engine!D53) -> 64180 | D29: =IF(ZP_Engine!E53="","",ZP_Engine!E53) -> 0.028612436
B30: =IF(ZP_Engine!C54="","",ZP_Engine!C54) -> Beverages | C30: =IF(ZP_Engine!C54="","",ZP_Engine!D54) -> 55051 | D30: =IF(ZP_Engine!E54="","",ZP_Engine!E54) -> 0.024542587
B31: =IF(ZP_Engine!C55="","",ZP_Engine!C55) -> Dairy, Bread & Batter | C31: =IF(ZP_Engine!C55="","",ZP_Engine!D55) -> 55051 | D31: =IF(ZP_Engine!E55="","",ZP_Engine!E55) -> 0.024542587
B32: =IF(ZP_Engine!C56="","",ZP_Engine!C56) -> Biscuits | C32: =IF(ZP_Engine!C56="","",ZP_Engine!D56) -> 25007.6 | D32: =IF(ZP_Engine!E56="","",ZP_Engine!E56) -> 0.011148775
B34: How to use
B35: 1. Change the yellow cells; charts, KPIs and the table recalculate.
B36: 2. "Group by" is the X axis; "Value field" + "Aggregation" is the Y axis.
B37: 3. "Split by" stacks the second chart by a second dimension.
B38: 4. Filters apply to every chart and KPI on this page.
B39: 5. Long lists (Country, City, Owner, Product) show the 20 most
B40: frequent items only. Dimensions with fewer items leave gaps.

Sheet ZP_Engine
A1: Calculation engine - do not edit. Drives the dashboard from the dropdown choices.
A2: dim # | B2: =MATCH('Zepto Dashboard'!$C$5,ZP_Lists!$A$2:$A$7,0) -> 1
A3: dim data col | B3: =INDEX(ZP_Lists!$B$2:$B$7,B2) -> 1
A4: measure # | B4: =MATCH('Zepto Dashboard'!$C$6,ZP_Lists!$D$2:$D$8,0) -> 1
A5: measure data col | B5: =INDEX(ZP_Lists!$E$2:$E$8,B4) -> 10
A6: aggregation | B6: ='Zepto Dashboard'!$C$7 -> Sum
A7: split # | B7: =IF('Zepto Dashboard'!$C$8="None",0,MATCH('Zepto Dashboard'!$C$8,ZP_Lists!$A$2:$A$7,0)) -> 0
A8: split data col | B8: =IF(B7=0,1,INDEX(ZP_Lists!$B$2:$B$7,B7)) -> 1
A9: top N | B9: ='Zepto Dashboard'!$C$10 -> 12
A10: sort | B10: ='Zepto Dashboard'!$C$9 -> Value: high to low
A11: crit: Category | B11: =IF('Zepto Dashboard'!$C$12="All","*",'Zepto Dashboard'!$C$12) -> *
A12: crit: Stock status | B12: =IF('Zepto Dashboard'!$C$13="All","*",'Zepto Dashboard'!$C$13) -> *
A13: crit: Weight category | B13: =IF('Zepto Dashboard'!$C$14="All","*",'Zepto Dashboard'!$C$14) -> *
A14: crit: Discount band | B14: =IF('Zepto Dashboard'!$C$15="All","*",'Zepto Dashboard'!$C$15) -> *
A18: split criteria | F18: =IF($B$7=0,"*",IF(INDEX(ZP_Lists!$L$2:$Q$21,1,$B$7)="","",INDEX(ZP_Lists!$L$2:$Q$21,1,$B$7))) -> * | G18: =IF($B$7=0,"",IF(INDEX(ZP_Lists!$L$2:$Q$21,2,$B$7)="","",INDEX(ZP_Lists!$L$2:$Q$21,2,$B$7))) | H18: =IF($B$7=0,"",IF(INDEX(ZP_Lists!$L$2:$Q$21,3,$B$7)="","",INDEX(ZP_Lists!$L$2:$Q$21,3,$B$7))) | I18: =IF($B$7=0,"",IF(INDEX(ZP_Lists!$L$2:$Q$21,4,$B$7)="","",INDEX(ZP_Lists!$L$2:$Q$21,4,$B$7))) | J18: =IF($B$7=0,"",IF(INDEX(ZP_Lists!$L$2:$Q$21,5,$B$7)="","",INDEX(ZP_Lists!$L$2:$Q$21,5,$B$7)))
A19: members -> | B19: member | C19: value | D19: rank | F19: =IF(F18="*","All",F18) -> All | G19: =IF(G18="*","All",G18) | H19: =IF(H18="*","All",H18) | I19: =IF(I18="*","All",I18) | J19: =IF(J18="*","All",J18)
A20: 1 | B20: =IF(INDEX(ZP_Lists!$L$2:$Q$21,A20,$B$2)="","",INDEX(ZP_Lists!$L$2:$Q$21,A20,$B$2)) -> Beverages | C20: =IF(B20="","",IF($B$6="Count",COUNTIFS(INDEX(ZPD,0,$B$3),B20,Zepto_Data!$A$2:$A$3732,$B$11,Zepto_Data!$L$2:$L$3732,$B$12,Zepto_Data!$K$2:$K$3732,$B$13,Zepto_Data!$M$2:$M$3732,$B$14),IF($B$6="Sum",SUMIFS(INDEX(ZPD,0,$B$5),INDEX(ZPD,0,$B$3),B20,Zepto_Data!$A$2:$A$3732,$B$11,Zepto_Data!$L$2:$L$3732,$B$12,Zepto_Data!$K$2:$K$3732,$B$13,Zepto_Data!$M$2:$M$3732,$B$14),IFERROR(SUMIFS(INDEX(ZPD,0,$B$5),INDEX(ZPD,0,$B$3),B20,Zepto_Data!$A$2:$A$3732,$B$11,Zepto_Data!$L$2:$L$3732,$B$12,Zepto_Data!$K$2:$K$3732,$B$13,Zepto_Data!$M$2:$M$3732,$B$14)/COUNTIFS(INDEX(ZPD,0,$B$3),B20,Zepto_Data!$A$2:$A$3732,$B$11,Zepto_Data!$L$2:$L$3732,$B$12,Zepto_Data!$K$2:$K$3732,$B$13,Zepto_Data!$M$2:$M$3732,$B$14),0)))) -> 55051 | D20: =IF(B20="","",IF($B$10="Natural order",A20,IF($B$10="Value: high to low",SUMPRODUCT(($B$20:$B$39<>"")*($C$20:$C$39>C20))+SUMPRODUCT(($B$20:B20<>"")*($C$20:C20=C20)),SUMPRODUCT(($B$20:$B$39<>"")*($C$20:$C$39<C20))+SUMPRODUCT(($B$20:B20<>"")*($C$20:C20=C20))))) -> 10 | F20: =IF(OR($B20="",F$18=""),"",IF($B$6="Count",COUNTIFS(INDEX(ZPD,0,$B$3),$B20,INDEX(ZPD,0,$B$8),F$18,Zepto_Data!$A$2:$A$3732,$B$11,Zepto_Data!$L$2:$L$3732,$B$12,Zepto_Data!$K$2:$K$3732,$B$13,Zepto_Data!$M$2:$M$3732,$B$14),IF($B$6="Sum",SUMIFS(INDEX(ZPD,0,$B$5),INDEX(ZPD,0,$B$3),$B20,INDEX(ZPD,0,$B$8),F$18,Zepto_Data!$A$2:$A$3732,$B$11,Zepto_Data!$L$2:$L$3732,$B$12,Zepto_Data!$K$2:$K$3732,$B$13,Zepto_Data!$M$2:$M$3732,$B$14),IFERROR(SUMIFS(INDEX(ZPD,0,$B$5),INDEX(ZPD,0,$B$3),$B20,INDEX(ZPD,0,$B$8),F$18,Zepto_Data!$A$2:$A$3732,$B$11,Zepto_Data!$L$2:$L$3732,$B$12,Zepto_Data!$K$2:$K$3732,$B$13,Zepto_Data!$M$2:$M$3732,$B$14)/COUNTIFS(INDEX(ZPD,0,$B$3),$B20,INDEX(ZPD,0,$B$8),F$18,Zepto_Data!$A$2:$A$3732,$B$11,Zepto_Data!$L$2:$L$3732,$B$12,Zepto_Data!$K$2:$K$3732,$B$13,Zepto_Data!$M$2:$M$3732,$B$14),0)))) -> 55051 | G20: =IF(OR($B20="",G$18=""),"",IF($B$6="Count",COUNTIFS(INDEX(ZPD,0,$B$3),$B20,INDEX(ZPD,0,$B$8),G$18,Zepto_Data!$A$2:$A$3732,$B$11,Zepto_Data!$L$2:$L$3732,$B$12,Zepto_Data!$K$2:$K$3732,$B$13,Zepto_Data!$M$2:$M$3732,$B$14),IF($B$6="Sum",SUMIFS(INDEX(ZPD,0,$B$5),INDEX(ZPD,0,$B$3),$B20,INDEX(ZPD,0,$B$8),G$18,Zepto_Data!$A$2:$A$3732,$B$11,Zepto_Data!$L$2:$L$3732,$B$12,Zepto_Data!$K$2:$K$3732,$B$13,Zepto_Data!$M$2:$M$3732,$B$14),IFERROR(SUMIFS(INDEX(ZPD,0,$B$5),INDEX(ZPD,0,$B$3),$B20,INDEX(ZPD,0,$B$8),G$18,Zepto_Data!$A$2:$A$3732,$B$11,Zepto_Data!$L$2:$L$3732,$B$12,Zepto_Data!$K$2:$K$3732,$B$13,Zepto_Data!$M$2:$M$3732,$B$14)/COUNTIFS(INDEX(ZPD,0,$B$3),$B20,INDEX(ZPD,0,$B$8),G$18,Zepto_Data!$A$2:$A$3732,$B$11,Zepto_Data!$L$2:$L$3732,$B$12,Zepto_Data!$K$2:$K$3732,$B$13,Zepto_Data!$M$2:$M$3732,$B$14),0)))) | H20: =IF(OR($B20="",H$18=""),"",IF($B$6="Count",COUNTIFS(INDEX(ZPD,0,$B$3),$B20,INDEX(ZPD,0,$B$8),H$18,Zepto_Data!$A$2:$A$3732,$B$11,Zepto_Data!$L$2:$L$3732,$B$12,Zepto_Data!$K$2:$K$3732,$B$13,Zepto_Data!$M$2:$M$3732,$B$14),IF($B$6="Sum",SUMIFS(INDEX(ZPD,0,$B$5),INDEX(ZPD,0,$B$3),$B20,INDEX(ZPD,0,$B$8),H$18,Zepto_Data!$A$2:$A$3732,$B$11,Zepto_Data!$L$2:$L$3732,$B$12,Zepto_Data!$K$2:$K$3732,$B$13,Zepto_Data!$M$2:$M$3732,$B$14),IFERROR(SUMIFS(INDEX(ZPD,0,$B$5),INDEX(ZPD,0,$B$3),$B20,INDEX(ZPD,0,$B$8),H$18,Zepto_Data!$A$2:$A$3732,$B$11,Zepto_Data!$L$2:$L$3732,$B$12,Zepto_Data!$K$2:$K$3732,$B$13,Zepto_Data!$M$2:$M$3732,$B$14)/COUNTIFS(INDEX(ZPD,0,$B$3),$B20,INDEX(ZPD,0,$B$8),H$18,Zepto_Data!$A$2:$A$3732,$B$11,Zepto_Data!$L$2:$L$3732,$B$12,Zepto_Data!$K$2:$K$3732,$B$13,Zepto_Data!$M$2:$M$3732,$B$14),0)))) | I20: =IF(OR($B20="",I$18=""),"",IF($B$6="Count",COUNTIFS(INDEX(ZPD,0,$B$3),$B20,INDEX(ZPD,0,$B$8),I$18,Zepto_Data!$A$2:$A$3732,$B$11,Zepto_Data!$L$2:$L$3732,$B$12,Zepto_Data!$K$2:$K$3732,$B$13,Zepto_Data!$M$2:$M$3732,$B$14),IF($B$6="Sum",SUMIFS(INDEX(ZPD,0,$B$5),INDEX(ZPD,0,$B$3),$B20,INDEX(ZPD,0,$B$8),I$18,Zepto_Data!$A$2:$A$3732,$B$11,Zepto_Data!$L$2:$L$3732,$B$12,Zepto_Data!$K$2:$K$3732,$B$13,Zepto_Data!$M$2:$M$3732,$B$14),IFERROR(SUMIFS(INDEX(ZPD,0,$B$5),INDEX(ZPD,0,$B$3),$B20,INDEX(ZPD,0,$B$8),I$18,Zepto_Data!$A$2:$A$3732,$B$11,Zepto_Data!$L$2:$L$3732,$B$12,Zepto_Data!$K$2:$K$3732,$B$13,Zepto_Data!$M$2:$M$3732,$B$14)/COUNTIFS(INDEX(ZPD,0,$B$3),$B20,INDEX(ZPD,0,$B$8),I$18,Zepto_Data!$A$2:$A$3732,$B$11,Zepto_Data!$L$2:$L$3732,$B$12,Zepto_Data!$K$2:$K$3732,$B$13,Zepto_Data!$M$2:$M$3732,$B$14),0)))) | J20: =IF(OR($B20="",J$18=""),"",IF($B$6="Count",COUNTIFS(INDEX(ZPD,0,$B$3),$B20,INDEX(ZPD,0,$B$8),J$18,Zepto_Data!$A$2:$A$3732,$B$11,Zepto_Data!$L$2:$L$3732,$B$12,Zepto_Data!$K$2:$K$3732,$B$13,Zepto_Data!$M$2:$M$3732,$B$14),IF($B$6="Sum",SUMIFS(INDEX(ZPD,0,$B$5),INDEX(ZPD,0,$B$3),$B20,INDEX(ZPD,0,$B$8),J$18,Zepto_Data!$A$2:$A$3732,$B$11,Zepto_Data!$L$2:$L$3732,$B$12,Zepto_Data!$K$2:$K$3732,$B$13,Zepto_Data!$M$2:$M$3732,$B$14),IFERROR(SUMIFS(INDEX(ZPD,0,$B$5),INDEX(ZPD,0,$B$3),$B20,INDEX(ZPD,0,$B$8),J$18,Zepto_Data!$A$2:$A$3732,$B$11,Zepto_Data!$L$2:$L$3732,$B$12,Zepto_Data!$K$2:$K$3732,$B$13,Zepto_Data!$M$2:$M$3732,$B$14)/COUNTIFS(INDEX(ZPD,0,$B$3),$B20,INDEX(ZPD,0,$B$8),J$18,Zepto_Data!$A$2:$A$3732,$B$11,Zepto_Data!$L$2:$L$3732,$B$12,Zepto_Data!$K$2:$K$3732,$B$13,Zepto_Data!$M$2:$M$3732,$B$14),0))))
A21: 2 | B21: =IF(INDEX(ZP_Lists!$L$2:$Q$21,A21,$B$2)="","",INDEX(ZP_Lists!$L$2:$Q$21,A21,$B$2)) -> Biscuits | C21: =IF(B21="","",IF($B$6="Count",COUNTIFS(INDEX(ZPD,0,$B$3),B21,Zepto_Data!$A$2:$A$3732,$B$11,Zepto_Data!$L$2:$L$3732,$B$12,Zepto_Data!$K$2:$K$3732,$B$13,Zepto_Data!$M$2:$M$3732,$B$14),IF($B$6="Sum",SUMIFS(INDEX(ZPD,0,$B$5),INDEX(ZPD,0,$B$3),B21,Zepto_Data!$A$2:$A$3732,$B$11,Zepto_Data!$L$2:$L$3732,$B$12,Zepto_Data!$K$2:$K$3732,$B$13,Zepto_Data!$M$2:$M$3732,$B$14),IFERROR(SUMIFS(INDEX(ZPD,0,$B$5),INDEX(ZPD,0,$B$3),B21,Zepto_Data!$A$2:$A$3732,$B$11,Zepto_Data!$L$2:$L$3732,$B$12,Zepto_Data!$K$2:$K$3732,$B$13,Zepto_Data!$M$2:$M$3732,$B$14)/COUNTIFS(INDEX(ZPD,0,$B$3),B21,Zepto_Data!$A$2:$A$3732,$B$11,Zepto_Data!$L$2:$L$3732,$B$12,Zepto_Data!$K$2:$K$3732,$B$13,Zepto_Data!$M$2:$M$3732,$B$14),0)))) -> 25007.6 | D21: =IF(B21="","",IF($B$10="Natural order",A21,IF($B$10="Value: high to low",SUMPRODUCT(($B$20:$B$39<>"")*($C$20:$C$39>C21))+SUMPRODUCT(($B$20:B21<>"")*($C$20:C21=C21)),SUMPRODUCT(($B$20:$B$39<>"")*($C$20:$C$39<C21))+SUMPRODUCT(($B$20:B21<>"")*($C$20:C21=C21))))) -> 12 | F21: =IF(OR($B21="",F$18=""),"",IF($B$6="Count",COUNTIFS(INDEX(ZPD,0,$B$3),$B21,INDEX(ZPD,0,$B$8),F$18,Zepto_Data!$A$2:$A$3732,$B$11,Zepto_Data!$L$2:$L$3732,$B$12,Zepto_Data!$K$2:$K$3732,$B$13,Zepto_Data!$M$2:$M$3732,$B$14),IF($B$6="Sum",SUMIFS(INDEX(ZPD,0,$B$5),INDEX(ZPD,0,$B$3),$B21,INDEX(ZPD,0,$B$8),F$18,Zepto_Data!$A$2:$A$3732,$B$11,Zepto_Data!$L$2:$L$3732,$B$12,Zepto_Data!$K$2:$K$3732,$B$13,Zepto_Data!$M$2:$M$3732,$B$14),IFERROR(SUMIFS(INDEX(ZPD,0,$B$5),INDEX(ZPD,0,$B$3),$B21,INDEX(ZPD,0,$B$8),F$18,Zepto_Data!$A$2:$A$3732,$B$11,Zepto_Data!$L$2:$L$3732,$B$12,Zepto_Data!$K$2:$K$3732,$B$13,Zepto_Data!$M$2:$M$3732,$B$14)/COUNTIFS(INDEX(ZPD,0,$B$3),$B21,INDEX(ZPD,0,$B$8),F$18,Zepto_Data!$A$2:$A$3732,$B$11,Zepto_Data!$L$2:$L$3732,$B$12,Zepto_Data!$K$2:$K$3732,$B$13,Zepto_Data!$M$2:$M$3732,$B$14),0)))) -> 25007.6 | G21: =IF(OR($B21="",G$18=""),"",IF($B$6="Count",COUNTIFS(INDEX(ZPD,0,$B$3),$B21,INDEX(ZPD,0,$B$8),G$18,Zepto_Data!$A$2:$A$3732,$B$11,Zepto_Data!$L$2:$L$3732,$B$12,Zepto_Data!$K$2:$K$3732,$B$13,Zepto_Data!$M$2:$M$3732,$B$14),IF($B$6="Sum",SUMIFS(INDEX(ZPD,0,$B$5),INDEX(ZPD,0,$B$3),$B21,INDEX(ZPD,0,$B$8),G$18,Zepto_Data!$A$2:$A$3732,$B$11,Zepto_Data!$L$2:$L$3732,$B$12,Zepto_Data!$K$2:$K$3732,$B$13,Zepto_Data!$M$2:$M$3732,$B$14),IFERROR(SUMIFS(INDEX(ZPD,0,$B$5),INDEX(ZPD,0,$B$3),$B21,INDEX(ZPD,0,$B$8),G$18,Zepto_Data!$A$2:$A$3732,$B$11,Zepto_Data!$L$2:$L$3732,$B$12,Zepto_Data!$K$2:$K$3732,$B$13,Zepto_Data!$M$2:$M$3732,$B$14)/COUNTIFS(INDEX(ZPD,0,$B$3),$B21,INDEX(ZPD,0,$B$8),G$18,Zepto_Data!$A$2:$A$3732,$B$11,Zepto_Data!$L$2:$L$3732,$B$12,Zepto_Data!$K$2:$K$3732,$B$13,Zepto_Data!$M$2:$M$3732,$B$14),0)))) | H21: =IF(OR($B21="",H$18=""),"",IF($B$6="Count",COUNTIFS(INDEX(ZPD,0,$B$3),$B21,INDEX(ZPD,0,$B$8),H$18,Zepto_Data!$A$2:$A$3732,$B$11,Zepto_Data!$L$2:$L$3732,$B$12,Zepto_Data!$K$2:$K$3732,$B$13,Zepto_Data!$M$2:$M$3732,$B$14),IF($B$6="Sum",SUMIFS(INDEX(ZPD,0,$B$5),INDEX(ZPD,0,$B$3),$B21,INDEX(ZPD,0,$B$8),H$18,Zepto_Data!$A$2:$A$3732,$B$11,Zepto_Data!$L$2:$L$3732,$B$12,Zepto_Data!$K$2:$K$3732,$B$13,Zepto_Data!$M$2:$M$3732,$B$14),IFERROR(SUMIFS(INDEX(ZPD,0,$B$5),INDEX(ZPD,0,$B$3),$B21,INDEX(ZPD,0,$B$8),H$18,Zepto_Data!$A$2:$A$3732,$B$11,Zepto_Data!$L$2:$L$3732,$B$12,Zepto_Data!$K$2:$K$3732,$B$13,Zepto_Data!$M$2:$M$3732,$B$14)/COUNTIFS(INDEX(ZPD,0,$B$3),$B21,INDEX(ZPD,0,$B$8),H$18,Zepto_Data!$A$2:$A$3732,$B$11,Zepto_Data!$L$2:$L$3732,$B$12,Zepto_Data!$K$2:$K$3732,$B$13,Zepto_Data!$M$2:$M$3732,$B$14),0)))) | I21: =IF(OR($B21="",I$18=""),"",IF($B$6="Count",COUNTIFS(INDEX(ZPD,0,$B$3),$B21,INDEX(ZPD,0,$B$8),I$18,Zepto_Data!$A$2:$A$3732,$B$11,Zepto_Data!$L$2:$L$3732,$B$12,Zepto_Data!$K$2:$K$3732,$B$13,Zepto_Data!$M$2:$M$3732,$B$14),IF($B$6="Sum",SUMIFS(INDEX(ZPD,0,$B$5),INDEX(ZPD,0,$B$3),$B21,INDEX(ZPD,0,$B$8),I$18,Zepto_Data!$A$2:$A$3732,$B$11,Zepto_Data!$L$2:$L$3732,$B$12,Zepto_Data!$K$2:$K$3732,$B$13,Zepto_Data!$M$2:$M$3732,$B$14),IFERROR(SUMIFS(INDEX(ZPD,0,$B$5),INDEX(ZPD,0,$B$3),$B21,INDEX(ZPD,0,$B$8),I$18,Zepto_Data!$A$2:$A$3732,$B$11,Zepto_Data!$L$2:$L$3732,$B$12,Zepto_Data!$K$2:$K$3732,$B$13,Zepto_Data!$M$2:$M$3732,$B$14)/COUNTIFS(INDEX(ZPD,0,$B$3),$B21,INDEX(ZPD,0,$B$8),I$18,Zepto_Data!$A$2:$A$3732,$B$11,Zepto_Data!$L$2:$L$3732,$B$12,Zepto_Data!$K$2:$K$3732,$B$13,Zepto_Data!$M$2:$M$3732,$B$14),0)))) | J21: =IF(OR($B21="",J$18=""),"",IF($B$6="Count",COUNTIFS(INDEX(ZPD,0,$B$3),$B21,INDEX(ZPD,0,$B$8),J$18,Zepto_Data!$A$2:$A$3732,$B$11,Zepto_Data!$L$2:$L$3732,$B$12,Zepto_Data!$K$2:$K$3732,$B$13,Zepto_Data!$M$2:$M$3732,$B$14),IF($B$6="Sum",SUMIFS(INDEX(ZPD,0,$B$5),INDEX(ZPD,0,$B$3),$B21,INDEX(ZPD,0,$B$8),J$18,Zepto_Data!$A$2:$A$3732,$B$11,Zepto_Data!$L$2:$L$3732,$B$12,Zepto_Data!$K$2:$K$3732,$B$13,Zepto_Data!$M$2:$M$3732,$B$14),IFERROR(SUMIFS(INDEX(ZPD,0,$B$5),INDEX(ZPD,0,$B$3),$B21,INDEX(ZPD,0,$B$8),J$18,Zepto_Data!$A$2:$A$3732,$B$11,Zepto_Data!$L$2:$L$3732,$B$12,Zepto_Data!$K$2:$K$3732,$B$13,Zepto_Data!$M$2:$M$3732,$B$14)/COUNTIFS(INDEX(ZPD,0,$B$3),$B21,INDEX(ZPD,0,$B$8),J$18,Zepto_Data!$A$2:$A$3732,$B$11,Zepto_Data!$L$2:$L$3732,$B$12,Zepto_Data!$K$2:$K$3732,$B$13,Zepto_Data!$M$2:$M$3732,$B$14),0))))
A22: 3 | B22: =IF(INDEX(ZP_Lists!$L$2:$Q$21,A22,$B$2)="","",INDEX(ZP_Lists!$L$2:$Q$21,A22,$B$2)) -> Chocolates & Candies | C22: =IF(B22="","",IF($B$6="Count",COUNTIFS(INDEX(ZPD,0,$B$3),B22,Zepto_Data!$A$2:$A$3732,$B$11,Zepto_Data!$L$2:$L$3732,$B$12,Zepto_Data!$K$2:$K$3732,$B$13,Zepto_Data!$M$2:$M$3732,$B$14),IF($B$6="Sum",SUMIFS(INDEX(ZPD,0,$B$5),INDEX(ZPD,0,$B$3),B22,Zepto_Data!$A$2:$A$3732,$B$11,Zepto_Data!$L$2:$L$3732,$B$12,Zepto_Data!$K$2:$K$3732,$B$13,Zepto_Data!$M$2:$M$3732,$B$14),IFERROR(SUMIFS(INDEX(ZPD,0,$B$5),INDEX(ZPD,0,$B$3),B22,Zepto_Data!$A$2:$A$3732,$B$11,Zepto_Data!$L$2:$L$3732,$B$12,Zepto_Data!$K$2:$K$3732,$B$13,Zepto_Data!$M$2:$M$3732,$B$14)/COUNTIFS(INDEX(ZPD,0,$B$3),B22,Zepto_Data!$A$2:$A$3732,$B$11,Zepto_Data!$L$2:$L$3732,$B$12,Zepto_Data!$K$2:$K$3732,$B$13,Zepto_Data!$M$2:$M$3732,$B$14),0)))) -> 224385 | D22: =IF(B22="","",IF($B$10="Natural order",A22,IF($B$10="Value: high to low",SUMPRODUCT(($B$20:$B$39<>"")*($C$20:$C$39>C22))+SUMPRODUCT(($B$20:B22<>"")*($C$20:C22=C22)),SUMPRODUCT(($B$20:$B$39<>"")*($C$20:$C$39<C22))+SUMPRODUCT(($B$20:B22<>"")*($C$20:C22=C22))))) -> 5 | F22: =IF(OR($B22="",F$18=""),"",IF($B$6="Count",COUNTIFS(INDEX(ZPD,0,$B$3),$B22,INDEX(ZPD,0,$B$8),F$18,Zepto_Data!$A$2:$A$3732,$B$11,Zepto_Data!$L$2:$L$3732,$B$12,Zepto_Data!$K$2:$K$3732,$B$13,Zepto_Data!$M$2:$M$3732,$B$14),IF($B$6="Sum",SUMIFS(INDEX(ZPD,0,$B$5),INDEX(ZPD,0,$B$3),$B22,INDEX(ZPD,0,$B$8),F$18,Zepto_Data!$A$2:$A$3732,$B$11,Zepto_Data!$L$2:$L$3732,$B$12,Zepto_Data!$K$2:$K$3732,$B$13,Zepto_Data!$M$2:$M$3732,$B$14),IFERROR(SUMIFS(INDEX(ZPD,0,$B$5),INDEX(ZPD,0,$B$3),$B22,INDEX(ZPD,0,$B$8),F$18,Zepto_Data!$A$2:$A$3732,$B$11,Zepto_Data!$L$2:$L$3732,$B$12,Zepto_Data!$K$2:$K$3732,$B$13,Zepto_Data!$M$2:$M$3732,$B$14)/COUNTIFS(INDEX(ZPD,0,$B$3),$B22,INDEX(ZPD,0,$B$8),F$18,Zepto_Data!$A$2:$A$3732,$B$11,Zepto_Data!$L$2:$L$3732,$B$12,Zepto_Data!$K$2:$K$3732,$B$13,Zepto_Data!$M$2:$M$3732,$B$14),0)))) -> 224385 | G22: =IF(OR($B22="",G$18=""),"",IF($B$6="Count",COUNTIFS(INDEX(ZPD,0,$B$3),$B22,INDEX(ZPD,0,$B$8),G$18,Zepto_Data!$A$2:$A$3732,$B$11,Zepto_Data!$L$2:$L$3732,$B$12,Zepto_Data!$K$2:$K$3732,$B$13,Zepto_Data!$M$2:$M$3732,$B$14),IF($B$6="Sum",SUMIFS(INDEX(ZPD,0,$B$5),INDEX(ZPD,0,$B$3),$B22,INDEX(ZPD,0,$B$8),G$18,Zepto_Data!$A$2:$A$3732,$B$11,Zepto_Data!$L$2:$L$3732,$B$12,Zepto_Data!$K$2:$K$3732,$B$13,Zepto_Data!$M$2:$M$3732,$B$14),IFERROR(SUMIFS(INDEX(ZPD,0,$B$5),INDEX(ZPD,0,$B$3),$B22,INDEX(ZPD,0,$B$8),G$18,Zepto_Data!$A$2:$A$3732,$B$11,Zepto_Data!$L$2:$L$3732,$B$12,Zepto_Data!$K$2:$K$3732,$B$13,Zepto_Data!$M$2:$M$3732,$B$14)/COUNTIFS(INDEX(ZPD,0,$B$3),$B22,INDEX(ZPD,0,$B$8),G$18,Zepto_Data!$A$2:$A$3732,$B$11,Zepto_Data!$L$2:$L$3732,$B$12,Zepto_Data!$K$2:$K$3732,$B$13,Zepto_Data!$M$2:$M$3732,$B$14),0)))) | H22: =IF(OR($B22="",H$18=""),"",IF($B$6="Count",COUNTIFS(INDEX(ZPD,0,$B$3),$B22,INDEX(ZPD,0,$B$8),H$18,Zepto_Data!$A$2:$A$3732,$B$11,Zepto_Data!$L$2:$L$3732,$B$12,Zepto_Data!$K$2:$K$3732,$B$13,Zepto_Data!$M$2:$M$3732,$B$14),IF($B$6="Sum",SUMIFS(INDEX(ZPD,0,$B$5),INDEX(ZPD,0,$B$3),$B22,INDEX(ZPD,0,$B$8),H$18,Zepto_Data!$A$2:$A$3732,$B$11,Zepto_Data!$L$2:$L$3732,$B$12,Zepto_Data!$K$2:$K$3732,$B$13,Zepto_Data!$M$2:$M$3732,$B$14),IFERROR(SUMIFS(INDEX(ZPD,0,$B$5),INDEX(ZPD,0,$B$3),$B22,INDEX(ZPD,0,$B$8),H$18,Zepto_Data!$A$2:$A$3732,$B$11,Zepto_Data!$L$2:$L$3732,$B$12,Zepto_Data!$K$2:$K$3732,$B$13,Zepto_Data!$M$2:$M$3732,$B$14)/COUNTIFS(INDEX(ZPD,0,$B$3),$B22,INDEX(ZPD,0,$B$8),H$18,Zepto_Data!$A$2:$A$3732,$B$11,Zepto_Data!$L$2:$L$3732,$B$12,Zepto_Data!$K$2:$K$3732,$B$13,Zepto_Data!$M$2:$M$3732,$B$14),0)))) | I22: =IF(OR($B22="",I$18=""),"",IF($B$6="Count",COUNTIFS(INDEX(ZPD,0,$B$3),$B22,INDEX(ZPD,0,$B$8),I$18,Zepto_Data!$A$2:$A$3732,$B$11,Zepto_Data!$L$2:$L$3732,$B$12,Zepto_Data!$K$2:$K$3732,$B$13,Zepto_Data!$M$2:$M$3732,$B$14),IF($B$6="Sum",SUMIFS(INDEX(ZPD,0,$B$5),INDEX(ZPD,0,$B$3),$B22,INDEX(ZPD,0,$B$8),I$18,Zepto_Data!$A$2:$A$3732,$B$11,Zepto_Data!$L$2:$L$3732,$B$12,Zepto_Data!$K$2:$K$3732,$B$13,Zepto_Data!$M$2:$M$3732,$B$14),IFERROR(SUMIFS(INDEX(ZPD,0,$B$5),INDEX(ZPD,0,$B$3),$B22,INDEX(ZPD,0,$B$8),I$18,Zepto_Data!$A$2:$A$3732,$B$11,Zepto_Data!$L$2:$L$3732,$B$12,Zepto_Data!$K$2:$K$3732,$B$13,Zepto_Data!$M$2:$M$3732,$B$14)/COUNTIFS(INDEX(ZPD,0,$B$3),$B22,INDEX(ZPD,0,$B$8),I$18,Zepto_Data!$A$2:$A$3732,$B$11,Zepto_Data!$L$2:$L$3732,$B$12,Zepto_Data!$K$2:$K$3732,$B$13,Zepto_Data!$M$2:$M$3732,$B$14),0)))) | J22: =IF(OR($B22="",J$18=""),"",IF($B$6="Count",COUNTIFS(INDEX(ZPD,0,$B$3),$B22,INDEX(ZPD,0,$B$8),J$18,Zepto_Data!$A$2:$A$3732,$B$11,Zepto_Data!$L$2:$L$3732,$B$12,Zepto_Data!$K$2:$K$3732,$B$13,Zepto_Data!$M$2:$M$3732,$B$14),IF($B$6="Sum",SUMIFS(INDEX(ZPD,0,$B$5),INDEX(ZPD,0,$B$3),$B22,INDEX(ZPD,0,$B$8),J$18,Zepto_Data!$A$2:$A$3732,$B$11,Zepto_Data!$L$2:$L$3732,$B$12,Zepto_Data!$K$2:$K$3732,$B$13,Zepto_Data!$M$2:$M$3732,$B$14),IFERROR(SUMIFS(INDEX(ZPD,0,$B$5),INDEX(ZPD,0,$B$3),$B22,INDEX(ZPD,0,$B$8),J$18,Zepto_Data!$A$2:$A$3732,$B$11,Zepto_Data!$L$2:$L$3732,$B$12,Zepto_Data!$K$2:$K$3732,$B$13,Zepto_Data!$M$2:$M$3732,$B$14)/COUNTIFS(INDEX(ZPD,0,$B$3),$B22,INDEX(ZPD,0,$B$8),J$18,Zepto_Data!$A$2:$A$3732,$B$11,Zepto_Data!$L$2:$L$3732,$B$12,Zepto_Data!$K$2:$K$3732,$B$13,Zepto_Data!$M$2:$M$3732,$B$14),0))))
A23: 4 | B23: =IF(INDEX(ZP_Lists!$L$2:$Q$21,A23,$B$2)="","",INDEX(ZP_Lists!$L$2:$Q$21,A23,$B$2)) -> Cooking Essentials | C23: =IF(B23="","",IF($B$6="Count",COUNTIFS(INDEX(ZPD,0,$B$3),B23,Zepto_Data!$A$2:$A$3732,$B$11,Zepto_Data!$L$2:$L$3732,$B$12,Zepto_Data!$K$2:$K$3732,$B$13,Zepto_Data!$M$2:$M$3732,$B$14),IF($B$6="Sum",SUMIFS(INDEX(ZPD,0,$B$5),INDEX(ZPD,0,$B$3),B23,Zepto_Data!$A$2:$A$3732,$B$11,Zepto_Data!$L$2:$L$3732,$B$12,Zepto_Data!$K$2:$K$3732,$B$13,Zepto_Data!$M$2:$M$3732,$B$14),IFERROR(SUMIFS(INDEX(ZPD,0,$B$5),INDEX(ZPD,0,$B$3),B23,Zepto_Data!$A$2:$A$3732,$B$11,Zepto_Data!$L$2:$L$3732,$B$12,Zepto_Data!$K$2:$K$3732,$B$13,Zepto_Data!$M$2:$M$3732,$B$14)/COUNTIFS(INDEX(ZPD,0,$B$3),B23,Zepto_Data!$A$2:$A$3732,$B$11,Zepto_Data!$L$2:$L$3732,$B$12,Zepto_Data!$K$2:$K$3732,$B$13,Zepto_Data!$M$2:$M$3732,$B$14),0)))) -> 337369 | D23: =IF(B23="","",IF($B$10="Natural order",A23,IF($B$10="Value: high to low",SUMPRODUCT(($B$20:$B$39<>"")*($C$20:$C$39>C23))+SUMPRODUCT(($B$20:B23<>"")*($C$20:C23=C23)),SUMPRODUCT(($B$20:$B$39<>"")*($C$20:$C$39<C23))+SUMPRODUCT(($B$20:B23<>"")*($C$20:C23=C23))))) -> 1 | F23: =IF(OR($B23="",F$18=""),"",IF($B$6="Count",COUNTIFS(INDEX(ZPD,0,$B$3),$B23,INDEX(ZPD,0,$B$8),F$18,Zepto_Data!$A$2:$A$3732,$B$11,Zepto_Data!$L$2:$L$3732,$B$12,Zepto_Data!$K$2:$K$3732,$B$13,Zepto_Data!$M$2:$M$3732,$B$14),IF($B$6="Sum",SUMIFS(INDEX(ZPD,0,$B$5),INDEX(ZPD,0,$B$3),$B23,INDEX(ZPD,0,$B$8),F$18,Zepto_Data!$A$2:$A$3732,$B$11,Zepto_Data!$L$2:$L$3732,$B$12,Zepto_Data!$K$2:$K$3732,$B$13,Zepto_Data!$M$2:$M$3732,$B$14),IFERROR(SUMIFS(INDEX(ZPD,0,$B$5),INDEX(ZPD,0,$B$3),$B23,INDEX(ZPD,0,$B$8),F$18,Zepto_Data!$A$2:$A$3732,$B$11,Zepto_Data!$L$2:$L$3732,$B$12,Zepto_Data!$K$2:$K$3732,$B$13,Zepto_Data!$M$2:$M$3732,$B$14)/COUNTIFS(INDEX(ZPD,0,$B$3),$B23,INDEX(ZPD,0,$B$8),F$18,Zepto_Data!$A$2:$A$3732,$B$11,Zepto_Data!$L$2:$L$3732,$B$12,Zepto_Data!$K$2:$K$3732,$B$13,Zepto_Data!$M$2:$M$3732,$B$14),0)))) -> 337369 | G23: =IF(OR($B23="",G$18=""),"",IF($B$6="Count",COUNTIFS(INDEX(ZPD,0,$B$3),$B23,INDEX(ZPD,0,$B$8),G$18,Zepto_Data!$A$2:$A$3732,$B$11,Zepto_Data!$L$2:$L$3732,$B$12,Zepto_Data!$K$2:$K$3732,$B$13,Zepto_Data!$M$2:$M$3732,$B$14),IF($B$6="Sum",SUMIFS(INDEX(ZPD,0,$B$5),INDEX(ZPD,0,$B$3),$B23,INDEX(ZPD,0,$B$8),G$18,Zepto_Data!$A$2:$A$3732,$B$11,Zepto_Data!$L$2:$L$3732,$B$12,Zepto_Data!$K$2:$K$3732,$B$13,Zepto_Data!$M$2:$M$3732,$B$14),IFERROR(SUMIFS(INDEX(ZPD,0,$B$5),INDEX(ZPD,0,$B$3),$B23,INDEX(ZPD,0,$B$8),G$18,Zepto_Data!$A$2:$A$3732,$B$11,Zepto_Data!$L$2:$L$3732,$B$12,Zepto_Data!$K$2:$K$3732,$B$13,Zepto_Data!$M$2:$M$3732,$B$14)/COUNTIFS(INDEX(ZPD,0,$B$3),$B23,INDEX(ZPD,0,$B$8),G$18,Zepto_Data!$A$2:$A$3732,$B$11,Zepto_Data!$L$2:$L$3732,$B$12,Zepto_Data!$K$2:$K$3732,$B$13,Zepto_Data!$M$2:$M$3732,$B$14),0)))) | H23: =IF(OR($B23="",H$18=""),"",IF($B$6="Count",COUNTIFS(INDEX(ZPD,0,$B$3),$B23,INDEX(ZPD,0,$B$8),H$18,Zepto_Data!$A$2:$A$3732,$B$11,Zepto_Data!$L$2:$L$3732,$B$12,Zepto_Data!$K$2:$K$3732,$B$13,Zepto_Data!$M$2:$M$3732,$B$14),IF($B$6="Sum",SUMIFS(INDEX(ZPD,0,$B$5),INDEX(ZPD,0,$B$3),$B23,INDEX(ZPD,0,$B$8),H$18,Zepto_Data!$A$2:$A$3732,$B$11,Zepto_Data!$L$2:$L$3732,$B$12,Zepto_Data!$K$2:$K$3732,$B$13,Zepto_Data!$M$2:$M$3732,$B$14),IFERROR(SUMIFS(INDEX(ZPD,0,$B$5),INDEX(ZPD,0,$B$3),$B23,INDEX(ZPD,0,$B$8),H$18,Zepto_Data!$A$2:$A$3732,$B$11,Zepto_Data!$L$2:$L$3732,$B$12,Zepto_Data!$K$2:$K$3732,$B$13,Zepto_Data!$M$2:$M$3732,$B$14)/COUNTIFS(INDEX(ZPD,0,$B$3),$B23,INDEX(ZPD,0,$B$8),H$18,Zepto_Data!$A$2:$A$3732,$B$11,Zepto_Data!$L$2:$L$3732,$B$12,Zepto_Data!$K$2:$K$3732,$B$13,Zepto_Data!$M$2:$M$3732,$B$14),0)))) | I23: =IF(OR($B23="",I$18=""),"",IF($B$6="Count",COUNTIFS(INDEX(ZPD,0,$B$3),$B23,INDEX(ZPD,0,$B$8),I$18,Zepto_Data!$A$2:$A$3732,$B$11,Zepto_Data!$L$2:$L$3732,$B$12,Zepto_Data!$K$2:$K$3732,$B$13,Zepto_Data!$M$2:$M$3732,$B$14),IF($B$6="Sum",SUMIFS(INDEX(ZPD,0,$B$5),INDEX(ZPD,0,$B$3),$B23,INDEX(ZPD,0,$B$8),I$18,Zepto_Data!$A$2:$A$3732,$B$11,Zepto_Data!$L$2:$L$3732,$B$12,Zepto_Data!$K$2:$K$3732,$B$13,Zepto_Data!$M$2:$M$3732,$B$14),IFERROR(SUMIFS(INDEX(ZPD,0,$B$5),INDEX(ZPD,0,$B$3),$B23,INDEX(ZPD,0,$B$8),I$18,Zepto_Data!$A$2:$A$3732,$B$11,Zepto_Data!$L$2:$L$3732,$B$12,Zepto_Data!$K$2:$K$3732,$B$13,Zepto_Data!$M$2:$M$3732,$B$14)/COUNTIFS(INDEX(ZPD,0,$B$3),$B23,INDEX(ZPD,0,$B$8),I$18,Zepto_Data!$A$2:$A$3732,$B$11,Zepto_Data!$L$2:$L$3732,$B$12,Zepto_Data!$K$2:$K$3732,$B$13,Zepto_Data!$M$2:$M$3732,$B$14),0)))) | J23: =IF(OR($B23="",J$18=""),"",IF($B$6="Count",COUNTIFS(INDEX(ZPD,0,$B$3),$B23,INDEX(ZPD,0,$B$8),J$18,Zepto_Data!$A$2:$A$3732,$B$11,Zepto_Data!$L$2:$L$3732,$B$12,Zepto_Data!$K$2:$K$3732,$B$13,Zepto_Data!$M$2:$M$3732,$B$14),IF($B$6="Sum",SUMIFS(INDEX(ZPD,0,$B$5),INDEX(ZPD,0,$B$3),$B23,INDEX(ZPD,0,$B$8),J$18,Zepto_Data!$A$2:$A$3732,$B$11,Zepto_Data!$L$2:$L$3732,$B$12,Zepto_Data!$K$2:$K$3732,$B$13,Zepto_Data!$M$2:$M$3732,$B$14),IFERROR(SUMIFS(INDEX(ZPD,0,$B$5),INDEX(ZPD,0,$B$3),$B23,INDEX(ZPD,0,$B$8),J$18,Zepto_Data!$A$2:$A$3732,$B$11,Zepto_Data!$L$2:$L$3732,$B$12,Zepto_Data!$K$2:$K$3732,$B$13,Zepto_Data!$M$2:$M$3732,$B$14)/COUNTIFS(INDEX(ZPD,0,$B$3),$B23,INDEX(ZPD,0,$B$8),J$18,Zepto_Data!$A$2:$A$3732,$B$11,Zepto_Data!$L$2:$L$3732,$B$12,Zepto_Data!$K$2:$K$3732,$B$13,Zepto_Data!$M$2:$M$3732,$B$14),0))))
A24: 5 | B24: =IF(INDEX(ZP_Lists!$L$2:$Q$21,A24,$B$2)="","",INDEX(ZP_Lists!$L$2:$Q$21,A24,$B$2)) -> Dairy, Bread & Batter | C24: =IF(B24="","",IF($B$6="Count",COUNTIFS(INDEX(ZPD,0,$B$3),B24,Zepto_Data!$A$2:$A$3732,$B$11,Zepto_Data!$L$2:$L$3732,$B$12,Zepto_Data!$K$2:$K$3732,$B$13,Zepto_Data!$M$2:$M$3732,$B$14),IF($B$6="Sum",SUMIFS(INDEX(ZPD,0,$B$5),INDEX(ZPD,0,$B$3),B24,Zepto_Data!$A$2:$A$3732,$B$11,Zepto_Data!$L$2:$L$3732,$B$12,Zepto_Data!$K$2:$K$3732,$B$13,Zepto_Data!$M$2:$M$3732,$B$14),IFERROR(SUMIFS(INDEX(ZPD,0,$B$5),INDEX(ZPD,0,$B$3),B24,Zepto_Data!$A$2:$A$3732,$B$11,Zepto_Data!$L$2:$L$3732,$B$12,Zepto_Data!$K$2:$K$3732,$B$13,Zepto_Data!$M$2:$M$3732,$B$14)/COUNTIFS(INDEX(ZPD,0,$B$3),B24,Zepto_Data!$A$2:$A$3732,$B$11,Zepto_Data!$L$2:$L$3732,$B$12,Zepto_Data!$K$2:$K$3732,$B$13,Zepto_Data!$M$2:$M$3732,$B$14),0)))) -> 55051 | D24: =IF(B24="","",IF($B$10="Natural order",A24,IF($B$10="Value: high to low",SUMPRODUCT(($B$20:$B$39<>"")*($C$20:$C$39>C24))+SUMPRODUCT(($B$20:B24<>"")*($C$20:C24=C24)),SUMPRODUCT(($B$20:$B$39<>"")*($C$20:$C$39<C24))+SUMPRODUCT(($B$20:B24<>"")*($C$20:C24=C24))))) -> 11 | F24: =IF(OR($B24="",F$18=""),"",IF($B$6="Count",COUNTIFS(INDEX(ZPD,0,$B$3),$B24,INDEX(ZPD,0,$B$8),F$18,Zepto_Data!$A$2:$A$3732,$B$11,Zepto_Data!$L$2:$L$3732,$B$12,Zepto_Data!$K$2:$K$3732,$B$13,Zepto_Data!$M$2:$M$3732,$B$14),IF($B$6="Sum",SUMIFS(INDEX(ZPD,0,$B$5),INDEX(ZPD,0,$B$3),$B24,INDEX(ZPD,0,$B$8),F$18,Zepto_Data!$A$2:$A$3732,$B$11,Zepto_Data!$L$2:$L$3732,$B$12,Zepto_Data!$K$2:$K$3732,$B$13,Zepto_Data!$M$2:$M$3732,$B$14),IFERROR(SUMIFS(INDEX(ZPD,0,$B$5),INDEX(ZPD,0,$B$3),$B24,INDEX(ZPD,0,$B$8),F$18,Zepto_Data!$A$2:$A$3732,$B$11,Zepto_Data!$L$2:$L$3732,$B$12,Zepto_Data!$K$2:$K$3732,$B$13,Zepto_Data!$M$2:$M$3732,$B$14)/COUNTIFS(INDEX(ZPD,0,$B$3),$B24,INDEX(ZPD,0,$B$8),F$18,Zepto_Data!$A$2:$A$3732,$B$11,Zepto_Data!$L$2:$L$3732,$B$12,Zepto_Data!$K$2:$K$3732,$B$13,Zepto_Data!$M$2:$M$3732,$B$14),0)))) -> 55051 | G24: =IF(OR($B24="",G$18=""),"",IF($B$6="Count",COUNTIFS(INDEX(ZPD,0,$B$3),$B24,INDEX(ZPD,0,$B$8),G$18,Zepto_Data!$A$2:$A$3732,$B$11,Zepto_Data!$L$2:$L$3732,$B$12,Zepto_Data!$K$2:$K$3732,$B$13,Zepto_Data!$M$2:$M$3732,$B$14),IF($B$6="Sum",SUMIFS(INDEX(ZPD,0,$B$5),INDEX(ZPD,0,$B$3),$B24,INDEX(ZPD,0,$B$8),G$18,Zepto_Data!$A$2:$A$3732,$B$11,Zepto_Data!$L$2:$L$3732,$B$12,Zepto_Data!$K$2:$K$3732,$B$13,Zepto_Data!$M$2:$M$3732,$B$14),IFERROR(SUMIFS(INDEX(ZPD,0,$B$5),INDEX(ZPD,0,$B$3),$B24,INDEX(ZPD,0,$B$8),G$18,Zepto_Data!$A$2:$A$3732,$B$11,Zepto_Data!$L$2:$L$3732,$B$12,Zepto_Data!$K$2:$K$3732,$B$13,Zepto_Data!$M$2:$M$3732,$B$14)/COUNTIFS(INDEX(ZPD,0,$B$3),$B24,INDEX(ZPD,0,$B$8),G$18,Zepto_Data!$A$2:$A$3732,$B$11,Zepto_Data!$L$2:$L$3732,$B$12,Zepto_Data!$K$2:$K$3732,$B$13,Zepto_Data!$M$2:$M$3732,$B$14),0)))) | H24: =IF(OR($B24="",H$18=""),"",IF($B$6="Count",COUNTIFS(INDEX(ZPD,0,$B$3),$B24,INDEX(ZPD,0,$B$8),H$18,Zepto_Data!$A$2:$A$3732,$B$11,Zepto_Data!$L$2:$L$3732,$B$12,Zepto_Data!$K$2:$K$3732,$B$13,Zepto_Data!$M$2:$M$3732,$B$14),IF($B$6="Sum",SUMIFS(INDEX(ZPD,0,$B$5),INDEX(ZPD,0,$B$3),$B24,INDEX(ZPD,0,$B$8),H$18,Zepto_Data!$A$2:$A$3732,$B$11,Zepto_Data!$L$2:$L$3732,$B$12,Zepto_Data!$K$2:$K$3732,$B$13,Zepto_Data!$M$2:$M$3732,$B$14),IFERROR(SUMIFS(INDEX(ZPD,0,$B$5),INDEX(ZPD,0,$B$3),$B24,INDEX(ZPD,0,$B$8),H$18,Zepto_Data!$A$2:$A$3732,$B$11,Zepto_Data!$L$2:$L$3732,$B$12,Zepto_Data!$K$2:$K$3732,$B$13,Zepto_Data!$M$2:$M$3732,$B$14)/COUNTIFS(INDEX(ZPD,0,$B$3),$B24,INDEX(ZPD,0,$B$8),H$18,Zepto_Data!$A$2:$A$3732,$B$11,Zepto_Data!$L$2:$L$3732,$B$12,Zepto_Data!$K$2:$K$3732,$B$13,Zepto_Data!$M$2:$M$3732,$B$14),0)))) | I24: =IF(OR($B24="",I$18=""),"",IF($B$6="Count",COUNTIFS(INDEX(ZPD,0,$B$3),$B24,INDEX(ZPD,0,$B$8),I$18,Zepto_Data!$A$2:$A$3732,$B$11,Zepto_Data!$L$2:$L$3732,$B$12,Zepto_Data!$K$2:$K$3732,$B$13,Zepto_Data!$M$2:$M$3732,$B$14),IF($B$6="Sum",SUMIFS(INDEX(ZPD,0,$B$5),INDEX(ZPD,0,$B$3),$B24,INDEX(ZPD,0,$B$8),I$18,Zepto_Data!$A$2:$A$3732,$B$11,Zepto_Data!$L$2:$L$3732,$B$12,Zepto_Data!$K$2:$K$3732,$B$13,Zepto_Data!$M$2:$M$3732,$B$14),IFERROR(SUMIFS(INDEX(ZPD,0,$B$5),INDEX(ZPD,0,$B$3),$B24,INDEX(ZPD,0,$B$8),I$18,Zepto_Data!$A$2:$A$3732,$B$11,Zepto_Data!$L$2:$L$3732,$B$12,Zepto_Data!$K$2:$K$3732,$B$13,Zepto_Data!$M$2:$M$3732,$B$14)/COUNTIFS(INDEX(ZPD,0,$B$3),$B24,INDEX(ZPD,0,$B$8),I$18,Zepto_Data!$A$2:$A$3732,$B$11,Zepto_Data!$L$2:$L$3732,$B$12,Zepto_Data!$K$2:$K$3732,$B$13,Zepto_Data!$M$2:$M$3732,$B$14),0)))) | J24: =IF(OR($B24="",J$18=""),"",IF($B$6="Count",COUNTIFS(INDEX(ZPD,0,$B$3),$B24,INDEX(ZPD,0,$B$8),J$18,Zepto_Data!$A$2:$A$3732,$B$11,Zepto_Data!$L$2:$L$3732,$B$12,Zepto_Data!$K$2:$K$3732,$B$13,Zepto_Data!$M$2:$M$3732,$B$14),IF($B$6="Sum",SUMIFS(INDEX(ZPD,0,$B$5),INDEX(ZPD,0,$B$3),$B24,INDEX(ZPD,0,$B$8),J$18,Zepto_Data!$A$2:$A$3732,$B$11,Zepto_Data!$L$2:$L$3732,$B$12,Zepto_Data!$K$2:$K$3732,$B$13,Zepto_Data!$M$2:$M$3732,$B$14),IFERROR(SUMIFS(INDEX(ZPD,0,$B$5),INDEX(ZPD,0,$B$3),$B24,INDEX(ZPD,0,$B$8),J$18,Zepto_Data!$A$2:$A$3732,$B$11,Zepto_Data!$L$2:$L$3732,$B$12,Zepto_Data!$K$2:$K$3732,$B$13,Zepto_Data!$M$2:$M$3732,$B$14)/COUNTIFS(INDEX(ZPD,0,$B$3),$B24,INDEX(ZPD,0,$B$8),J$18,Zepto_Data!$A$2:$A$3732,$B$11,Zepto_Data!$L$2:$L$3732,$B$12,Zepto_Data!$K$2:$K$3732,$B$13,Zepto_Data!$M$2:$M$3732,$B$14),0))))
A25: 6 | B25: =IF(INDEX(ZP_Lists!$L$2:$Q$21,A25,$B$2)="","",INDEX(ZP_Lists!$L$2:$Q$21,A25,$B$2)) -> Fruits & Vegetables | C25: =IF(B25="","",IF($B$6="Count",COUNTIFS(INDEX(ZPD,0,$B$3),B25,Zepto_Data!$A$2:$A$3732,$B$11,Zepto_Data!$L$2:$L$3732,$B$12,Zepto_Data!$K$2:$K$3732,$B$13,Zepto_Data!$M$2:$M$3732,$B$14),IF($B$6="Sum",SUMIFS(INDEX(ZPD,0,$B$5),INDEX(ZPD,0,$B$3),B25,Zepto_Data!$A$2:$A$3732,$B$11,Zepto_Data!$L$2:$L$3732,$B$12,Zepto_Data!$K$2:$K$3732,$B$13,Zepto_Data!$M$2:$M$3732,$B$14),IFERROR(SUMIFS(INDEX(ZPD,0,$B$5),INDEX(ZPD,0,$B$3),B25,Zepto_Data!$A$2:$A$3732,$B$11,Zepto_Data!$L$2:$L$3732,$B$12,Zepto_Data!$K$2:$K$3732,$B$13,Zepto_Data!$M$2:$M$3732,$B$14)/COUNTIFS(INDEX(ZPD,0,$B$3),B25,Zepto_Data!$A$2:$A$3732,$B$11,Zepto_Data!$L$2:$L$3732,$B$12,Zepto_Data!$K$2:$K$3732,$B$13,Zepto_Data!$M$2:$M$3732,$B$14),0)))) -> 10846 | D25: =IF(B25="","",IF($B$10="Natural order",A25,IF($B$10="Value: high to low",SUMPRODUCT(($B$20:$B$39<>"")*($C$20:$C$39>C25))+SUMPRODUCT(($B$20:B25<>"")*($C$20:C25=C25)),SUMPRODUCT(($B$20:$B$39<>"")*($C$20:$C$39<C25))+SUMPRODUCT(($B$20:B25<>"")*($C$20:C25=C25))))) -> 14 | F25: =IF(OR($B25="",F$18=""),"",IF($B$6="Count",COUNTIFS(INDEX(ZPD,0,$B$3),$B25,INDEX(ZPD,0,$B$8),F$18,Zepto_Data!$A$2:$A$3732,$B$11,Zepto_Data!$L$2:$L$3732,$B$12,Zepto_Data!$K$2:$K$3732,$B$13,Zepto_Data!$M$2:$M$3732,$B$14),IF($B$6="Sum",SUMIFS(INDEX(ZPD,0,$B$5),INDEX(ZPD,0,$B$3),$B25,INDEX(ZPD,0,$B$8),F$18,Zepto_Data!$A$2:$A$3732,$B$11,Zepto_Data!$L$2:$L$3732,$B$12,Zepto_Data!$K$2:$K$3732,$B$13,Zepto_Data!$M$2:$M$3732,$B$14),IFERROR(SUMIFS(INDEX(ZPD,0,$B$5),INDEX(ZPD,0,$B$3),$B25,INDEX(ZPD,0,$B$8),F$18,Zepto_Data!$A$2:$A$3732,$B$11,Zepto_Data!$L$2:$L$3732,$B$12,Zepto_Data!$K$2:$K$3732,$B$13,Zepto_Data!$M$2:$M$3732,$B$14)/COUNTIFS(INDEX(ZPD,0,$B$3),$B25,INDEX(ZPD,0,$B$8),F$18,Zepto_Data!$A$2:$A$3732,$B$11,Zepto_Data!$L$2:$L$3732,$B$12,Zepto_Data!$K$2:$K$3732,$B$13,Zepto_Data!$M$2:$M$3732,$B$14),0)))) -> 10846 | G25: =IF(OR($B25="",G$18=""),"",IF($B$6="Count",COUNTIFS(INDEX(ZPD,0,$B$3),$B25,INDEX(ZPD,0,$B$8),G$18,Zepto_Data!$A$2:$A$3732,$B$11,Zepto_Data!$L$2:$L$3732,$B$12,Zepto_Data!$K$2:$K$3732,$B$13,Zepto_Data!$M$2:$M$3732,$B$14),IF($B$6="Sum",SUMIFS(INDEX(ZPD,0,$B$5),INDEX(ZPD,0,$B$3),$B25,INDEX(ZPD,0,$B$8),G$18,Zepto_Data!$A$2:$A$3732,$B$11,Zepto_Data!$L$2:$L$3732,$B$12,Zepto_Data!$K$2:$K$3732,$B$13,Zepto_Data!$M$2:$M$3732,$B$14),IFERROR(SUMIFS(INDEX(ZPD,0,$B$5),INDEX(ZPD,0,$B$3),$B25,INDEX(ZPD,0,$B$8),G$18,Zepto_Data!$A$2:$A$3732,$B$11,Zepto_Data!$L$2:$L$3732,$B$12,Zepto_Data!$K$2:$K$3732,$B$13,Zepto_Data!$M$2:$M$3732,$B$14)/COUNTIFS(INDEX(ZPD,0,$B$3),$B25,INDEX(ZPD,0,$B$8),G$18,Zepto_Data!$A$2:$A$3732,$B$11,Zepto_Data!$L$2:$L$3732,$B$12,Zepto_Data!$K$2:$K$3732,$B$13,Zepto_Data!$M$2:$M$3732,$B$14),0)))) | H25: =IF(OR($B25="",H$18=""),"",IF($B$6="Count",COUNTIFS(INDEX(ZPD,0,$B$3),$B25,INDEX(ZPD,0,$B$8),H$18,Zepto_Data!$A$2:$A$3732,$B$11,Zepto_Data!$L$2:$L$3732,$B$12,Zepto_Data!$K$2:$K$3732,$B$13,Zepto_Data!$M$2:$M$3732,$B$14),IF($B$6="Sum",SUMIFS(INDEX(ZPD,0,$B$5),INDEX(ZPD,0,$B$3),$B25,INDEX(ZPD,0,$B$8),H$18,Zepto_Data!$A$2:$A$3732,$B$11,Zepto_Data!$L$2:$L$3732,$B$12,Zepto_Data!$K$2:$K$3732,$B$13,Zepto_Data!$M$2:$M$3732,$B$14),IFERROR(SUMIFS(INDEX(ZPD,0,$B$5),INDEX(ZPD,0,$B$3),$B25,INDEX(ZPD,0,$B$8),H$18,Zepto_Data!$A$2:$A$3732,$B$11,Zepto_Data!$L$2:$L$3732,$B$12,Zepto_Data!$K$2:$K$3732,$B$13,Zepto_Data!$M$2:$M$3732,$B$14)/COUNTIFS(INDEX(ZPD,0,$B$3),$B25,INDEX(ZPD,0,$B$8),H$18,Zepto_Data!$A$2:$A$3732,$B$11,Zepto_Data!$L$2:$L$3732,$B$12,Zepto_Data!$K$2:$K$3732,$B$13,Zepto_Data!$M$2:$M$3732,$B$14),0)))) | I25: =IF(OR($B25="",I$18=""),"",IF($B$6="Count",COUNTIFS(INDEX(ZPD,0,$B$3),$B25,INDEX(ZPD,0,$B$8),I$18,Zepto_Data!$A$2:$A$3732,$B$11,Zepto_Data!$L$2:$L$3732,$B$12,Zepto_Data!$K$2:$K$3732,$B$13,Zepto_Data!$M$2:$M$3732,$B$14),IF($B$6="Sum",SUMIFS(INDEX(ZPD,0,$B$5),INDEX(ZPD,0,$B$3),$B25,INDEX(ZPD,0,$B$8),I$18,Zepto_Data!$A$2:$A$3732,$B$11,Zepto_Data!$L$2:$L$3732,$B$12,Zepto_Data!$K$2:$K$3732,$B$13,Zepto_Data!$M$2:$M$3732,$B$14),IFERROR(SUMIFS(INDEX(ZPD,0,$B$5),INDEX(ZPD,0,$B$3),$B25,INDEX(ZPD,0,$B$8),I$18,Zepto_Data!$A$2:$A$3732,$B$11,Zepto_Data!$L$2:$L$3732,$B$12,Zepto_Data!$K$2:$K$3732,$B$13,Zepto_Data!$M$2:$M$3732,$B$14)/COUNTIFS(INDEX(ZPD,0,$B$3),$B25,INDEX(ZPD,0,$B$8),I$18,Zepto_Data!$A$2:$A$3732,$B$11,Zepto_Data!$L$2:$L$3732,$B$12,Zepto_Data!$K$2:$K$3732,$B$13,Zepto_Data!$M$2:$M$3732,$B$14),0)))) | J25: =IF(OR($B25="",J$18=""),"",IF($B$6="Count",COUNTIFS(INDEX(ZPD,0,$B$3),$B25,INDEX(ZPD,0,$B$8),J$18,Zepto_Data!$A$2:$A$3732,$B$11,Zepto_Data!$L$2:$L$3732,$B$12,Zepto_Data!$K$2:$K$3732,$B$13,Zepto_Data!$M$2:$M$3732,$B$14),IF($B$6="Sum",SUMIFS(INDEX(ZPD,0,$B$5),INDEX(ZPD,0,$B$3),$B25,INDEX(ZPD,0,$B$8),J$18,Zepto_Data!$A$2:$A$3732,$B$11,Zepto_Data!$L$2:$L$3732,$B$12,Zepto_Data!$K$2:$K$3732,$B$13,Zepto_Data!$M$2:$M$3732,$B$14),IFERROR(SUMIFS(INDEX(ZPD,0,$B$5),INDEX(ZPD,0,$B$3),$B25,INDEX(ZPD,0,$B$8),J$18,Zepto_Data!$A$2:$A$3732,$B$11,Zepto_Data!$L$2:$L$3732,$B$12,Zepto_Data!$K$2:$K$3732,$B$13,Zepto_Data!$M$2:$M$3732,$B$14)/COUNTIFS(INDEX(ZPD,0,$B$3),$B25,INDEX(ZPD,0,$B$8),J$18,Zepto_Data!$A$2:$A$3732,$B$11,Zepto_Data!$L$2:$L$3732,$B$12,Zepto_Data!$K$2:$K$3732,$B$13,Zepto_Data!$M$2:$M$3732,$B$14),0))))
A26: 7 | B26: =IF(INDEX(ZP_Lists!$L$2:$Q$21,A26,$B$2)="","",INDEX(ZP_Lists!$L$2:$Q$21,A26,$B$2)) -> Health & Hygiene | C26: =IF(B26="","",IF($B$6="Count",COUNTIFS(INDEX(ZPD,0,$B$3),B26,Zepto_Data!$A$2:$A$3732,$B$11,Zepto_Data!$L$2:$L$3732,$B$12,Zepto_Data!$K$2:$K$3732,$B$13,Zepto_Data!$M$2:$M$3732,$B$14),IF($B$6="Sum",SUMIFS(INDEX(ZPD,0,$B$5),INDEX(ZPD,0,$B$3),B26,Zepto_Data!$A$2:$A$3732,$B$11,Zepto_Data!$L$2:$L$3732,$B$12,Zepto_Data!$K$2:$K$3732,$B$13,Zepto_Data!$M$2:$M$3732,$B$14),IFERROR(SUMIFS(INDEX(ZPD,0,$B$5),INDEX(ZPD,0,$B$3),B26,Zepto_Data!$A$2:$A$3732,$B$11,Zepto_Data!$L$2:$L$3732,$B$12,Zepto_Data!$K$2:$K$3732,$B$13,Zepto_Data!$M$2:$M$3732,$B$14)/COUNTIFS(INDEX(ZPD,0,$B$3),B26,Zepto_Data!$A$2:$A$3732,$B$11,Zepto_Data!$L$2:$L$3732,$B$12,Zepto_Data!$K$2:$K$3732,$B$13,Zepto_Data!$M$2:$M$3732,$B$14),0)))) -> 64180 | D26: =IF(B26="","",IF($B$10="Natural order",A26,IF($B$10="Value: high to low",SUMPRODUCT(($B$20:$B$39<>"")*($C$20:$C$39>C26))+SUMPRODUCT(($B$20:B26<>"")*($C$20:C26=C26)),SUMPRODUCT(($B$20:$B$39<>"")*($C$20:$C$39<C26))+SUMPRODUCT(($B$20:B26<>"")*($C$20:C26=C26))))) -> 9 | F26: =IF(OR($B26="",F$18=""),"",IF($B$6="Count",COUNTIFS(INDEX(ZPD,0,$B$3),$B26,INDEX(ZPD,0,$B$8),F$18,Zepto_Data!$A$2:$A$3732,$B$11,Zepto_Data!$L$2:$L$3732,$B$12,Zepto_Data!$K$2:$K$3732,$B$13,Zepto_Data!$M$2:$M$3732,$B$14),IF($B$6="Sum",SUMIFS(INDEX(ZPD,0,$B$5),INDEX(ZPD,0,$B$3),$B26,INDEX(ZPD,0,$B$8),F$18,Zepto_Data!$A$2:$A$3732,$B$11,Zepto_Data!$L$2:$L$3732,$B$12,Zepto_Data!$K$2:$K$3732,$B$13,Zepto_Data!$M$2:$M$3732,$B$14),IFERROR(SUMIFS(INDEX(ZPD,0,$B$5),INDEX(ZPD,0,$B$3),$B26,INDEX(ZPD,0,$B$8),F$18,Zepto_Data!$A$2:$A$3732,$B$11,Zepto_Data!$L$2:$L$3732,$B$12,Zepto_Data!$K$2:$K$3732,$B$13,Zepto_Data!$M$2:$M$3732,$B$14)/COUNTIFS(INDEX(ZPD,0,$B$3),$B26,INDEX(ZPD,0,$B$8),F$18,Zepto_Data!$A$2:$A$3732,$B$11,Zepto_Data!$L$2:$L$3732,$B$12,Zepto_Data!$K$2:$K$3732,$B$13,Zepto_Data!$M$2:$M$3732,$B$14),0)))) -> 64180 | G26: =IF(OR($B26="",G$18=""),"",IF($B$6="Count",COUNTIFS(INDEX(ZPD,0,$B$3),$B26,INDEX(ZPD,0,$B$8),G$18,Zepto_Data!$A$2:$A$3732,$B$11,Zepto_Data!$L$2:$L$3732,$B$12,Zepto_Data!$K$2:$K$3732,$B$13,Zepto_Data!$M$2:$M$3732,$B$14),IF($B$6="Sum",SUMIFS(INDEX(ZPD,0,$B$5),INDEX(ZPD,0,$B$3),$B26,INDEX(ZPD,0,$B$8),G$18,Zepto_Data!$A$2:$A$3732,$B$11,Zepto_Data!$L$2:$L$3732,$B$12,Zepto_Data!$K$2:$K$3732,$B$13,Zepto_Data!$M$2:$M$3732,$B$14),IFERROR(SUMIFS(INDEX(ZPD,0,$B$5),INDEX(ZPD,0,$B$3),$B26,INDEX(ZPD,0,$B$8),G$18,Zepto_Data!$A$2:$A$3732,$B$11,Zepto_Data!$L$2:$L$3732,$B$12,Zepto_Data!$K$2:$K$3732,$B$13,Zepto_Data!$M$2:$M$3732,$B$14)/COUNTIFS(INDEX(ZPD,0,$B$3),$B26,INDEX(ZPD,0,$B$8),G$18,Zepto_Data!$A$2:$A$3732,$B$11,Zepto_Data!$L$2:$L$3732,$B$12,Zepto_Data!$K$2:$K$3732,$B$13,Zepto_Data!$M$2:$M$3732,$B$14),0)))) | H26: =IF(OR($B26="",H$18=""),"",IF($B$6="Count",COUNTIFS(INDEX(ZPD,0,$B$3),$B26,INDEX(ZPD,0,$B$8),H$18,Zepto_Data!$A$2:$A$3732,$B$11,Zepto_Data!$L$2:$L$3732,$B$12,Zepto_Data!$K$2:$K$3732,$B$13,Zepto_Data!$M$2:$M$3732,$B$14),IF($B$6="Sum",SUMIFS(INDEX(ZPD,0,$B$5),INDEX(ZPD,0,$B$3),$B26,INDEX(ZPD,0,$B$8),H$18,Zepto_Data!$A$2:$A$3732,$B$11,Zepto_Data!$L$2:$L$3732,$B$12,Zepto_Data!$K$2:$K$3732,$B$13,Zepto_Data!$M$2:$M$3732,$B$14),IFERROR(SUMIFS(INDEX(ZPD,0,$B$5),INDEX(ZPD,0,$B$3),$B26,INDEX(ZPD,0,$B$8),H$18,Zepto_Data!$A$2:$A$3732,$B$11,Zepto_Data!$L$2:$L$3732,$B$12,Zepto_Data!$K$2:$K$3732,$B$13,Zepto_Data!$M$2:$M$3732,$B$14)/COUNTIFS(INDEX(ZPD,0,$B$3),$B26,INDEX(ZPD,0,$B$8),H$18,Zepto_Data!$A$2:$A$3732,$B$11,Zepto_Data!$L$2:$L$3732,$B$12,Zepto_Data!$K$2:$K$3732,$B$13,Zepto_Data!$M$2:$M$3732,$B$14),0)))) | I26: =IF(OR($B26="",I$18=""),"",IF($B$6="Count",COUNTIFS(INDEX(ZPD,0,$B$3),$B26,INDEX(ZPD,0,$B$8),I$18,Zepto_Data!$A$2:$A$3732,$B$11,Zepto_Data!$L$2:$L$3732,$B$12,Zepto_Data!$K$2:$K$3732,$B$13,Zepto_Data!$M$2:$M$3732,$B$14),IF($B$6="Sum",SUMIFS(INDEX(ZPD,0,$B$5),INDEX(ZPD,0,$B$3),$B26,INDEX(ZPD,0,$B$8),I$18,Zepto_Data!$A$2:$A$3732,$B$11,Zepto_Data!$L$2:$L$3732,$B$12,Zepto_Data!$K$2:$K$3732,$B$13,Zepto_Data!$M$2:$M$3732,$B$14),IFERROR(SUMIFS(INDEX(ZPD,0,$B$5),INDEX(ZPD,0,$B$3),$B26,INDEX(ZPD,0,$B$8),I$18,Zepto_Data!$A$2:$A$3732,$B$11,Zepto_Data!$L$2:$L$3732,$B$12,Zepto_Data!$K$2:$K$3732,$B$13,Zepto_Data!$M$2:$M$3732,$B$14)/COUNTIFS(INDEX(ZPD,0,$B$3),$B26,INDEX(ZPD,0,$B$8),I$18,Zepto_Data!$A$2:$A$3732,$B$11,Zepto_Data!$L$2:$L$3732,$B$12,Zepto_Data!$K$2:$K$3732,$B$13,Zepto_Data!$M$2:$M$3732,$B$14),0)))) | J26: =IF(OR($B26="",J$18=""),"",IF($B$6="Count",COUNTIFS(INDEX(ZPD,0,$B$3),$B26,INDEX(ZPD,0,$B$8),J$18,Zepto_Data!$A$2:$A$3732,$B$11,Zepto_Data!$L$2:$L$3732,$B$12,Zepto_Data!$K$2:$K$3732,$B$13,Zepto_Data!$M$2:$M$3732,$B$14),IF($B$6="Sum",SUMIFS(INDEX(ZPD,0,$B$5),INDEX(ZPD,0,$B$3),$B26,INDEX(ZPD,0,$B$8),J$18,Zepto_Data!$A$2:$A$3732,$B$11,Zepto_Data!$L$2:$L$3732,$B$12,Zepto_Data!$K$2:$K$3732,$B$13,Zepto_Data!$M$2:$M$3732,$B$14),IFERROR(SUMIFS(INDEX(ZPD,0,$B$5),INDEX(ZPD,0,$B$3),$B26,INDEX(ZPD,0,$B$8),J$18,Zepto_Data!$A$2:$A$3732,$B$11,Zepto_Data!$L$2:$L$3732,$B$12,Zepto_Data!$K$2:$K$3732,$B$13,Zepto_Data!$M$2:$M$3732,$B$14)/COUNTIFS(INDEX(ZPD,0,$B$3),$B26,INDEX(ZPD,0,$B$8),J$18,Zepto_Data!$A$2:$A$3732,$B$11,Zepto_Data!$L$2:$L$3732,$B$12,Zepto_Data!$K$2:$K$3732,$B$13,Zepto_Data!$M$2:$M$3732,$B$14),0))))
A27: 8 | B27: =IF(INDEX(ZP_Lists!$L$2:$Q$21,A27,$B$2)="","",INDEX(ZP_Lists!$L$2:$Q$21,A27,$B$2)) -> Home & Cleaning | C27: =IF(B27="","",IF($B$6="Count",COUNTIFS(INDEX(ZPD,0,$B$3),B27,Zepto_Data!$A$2:$A$3732,$B$11,Zepto_Data!$L$2:$L$3732,$B$12,Zepto_Data!$K$2:$K$3732,$B$13,Zepto_Data!$M$2:$M$3732,$B$14),IF($B$6="Sum",SUMIFS(INDEX(ZPD,0,$B$5),INDEX(ZPD,0,$B$3),B27,Zepto_Data!$A$2:$A$3732,$B$11,Zepto_Data!$L$2:$L$3732,$B$12,Zepto_Data!$K$2:$K$3732,$B$13,Zepto_Data!$M$2:$M$3732,$B$14),IFERROR(SUMIFS(INDEX(ZPD,0,$B$5),INDEX(ZPD,0,$B$3),B27,Zepto_Data!$A$2:$A$3732,$B$11,Zepto_Data!$L$2:$L$3732,$B$12,Zepto_Data!$K$2:$K$3732,$B$13,Zepto_Data!$M$2:$M$3732,$B$14)/COUNTIFS(INDEX(ZPD,0,$B$3),B27,Zepto_Data!$A$2:$A$3732,$B$11,Zepto_Data!$L$2:$L$3732,$B$12,Zepto_Data!$K$2:$K$3732,$B$13,Zepto_Data!$M$2:$M$3732,$B$14),0)))) -> 122661 | D27: =IF(B27="","",IF($B$10="Natural order",A27,IF($B$10="Value: high to low",SUMPRODUCT(($B$20:$B$39<>"")*($C$20:$C$39>C27))+SUMPRODUCT(($B$20:B27<>"")*($C$20:C27=C27)),SUMPRODUCT(($B$20:$B$39<>"")*($C$20:$C$39<C27))+SUMPRODUCT(($B$20:B27<>"")*($C$20:C27=C27))))) -> 8 | F27: =IF(OR($B27="",F$18=""),"",IF($B$6="Count",COUNTIFS(INDEX(ZPD,0,$B$3),$B27,INDEX(ZPD,0,$B$8),F$18,Zepto_Data!$A$2:$A$3732,$B$11,Zepto_Data!$L$2:$L$3732,$B$12,Zepto_Data!$K$2:$K$3732,$B$13,Zepto_Data!$M$2:$M$3732,$B$14),IF($B$6="Sum",SUMIFS(INDEX(ZPD,0,$B$5),INDEX(ZPD,0,$B$3),$B27,INDEX(ZPD,0,$B$8),F$18,Zepto_Data!$A$2:$A$3732,$B$11,Zepto_Data!$L$2:$L$3732,$B$12,Zepto_Data!$K$2:$K$3732,$B$13,Zepto_Data!$M$2:$M$3732,$B$14),IFERROR(SUMIFS(INDEX(ZPD,0,$B$5),INDEX(ZPD,0,$B$3),$B27,INDEX(ZPD,0,$B$8),F$18,Zepto_Data!$A$2:$A$3732,$B$11,Zepto_Data!$L$2:$L$3732,$B$12,Zepto_Data!$K$2:$K$3732,$B$13,Zepto_Data!$M$2:$M$3732,$B$14)/COUNTIFS(INDEX(ZPD,0,$B$3),$B27,INDEX(ZPD,0,$B$8),F$18,Zepto_Data!$A$2:$A$3732,$B$11,Zepto_Data!$L$2:$L$3732,$B$12,Zepto_Data!$K$2:$K$3732,$B$13,Zepto_Data!$M$2:$M$3732,$B$14),0)))) -> 122661 | G27: =IF(OR($B27="",G$18=""),"",IF($B$6="Count",COUNTIFS(INDEX(ZPD,0,$B$3),$B27,INDEX(ZPD,0,$B$8),G$18,Zepto_Data!$A$2:$A$3732,$B$11,Zepto_Data!$L$2:$L$3732,$B$12,Zepto_Data!$K$2:$K$3732,$B$13,Zepto_Data!$M$2:$M$3732,$B$14),IF($B$6="Sum",SUMIFS(INDEX(ZPD,0,$B$5),INDEX(ZPD,0,$B$3),$B27,INDEX(ZPD,0,$B$8),G$18,Zepto_Data!$A$2:$A$3732,$B$11,Zepto_Data!$L$2:$L$3732,$B$12,Zepto_Data!$K$2:$K$3732,$B$13,Zepto_Data!$M$2:$M$3732,$B$14),IFERROR(SUMIFS(INDEX(ZPD,0,$B$5),INDEX(ZPD,0,$B$3),$B27,INDEX(ZPD,0,$B$8),G$18,Zepto_Data!$A$2:$A$3732,$B$11,Zepto_Data!$L$2:$L$3732,$B$12,Zepto_Data!$K$2:$K$3732,$B$13,Zepto_Data!$M$2:$M$3732,$B$14)/COUNTIFS(INDEX(ZPD,0,$B$3),$B27,INDEX(ZPD,0,$B$8),G$18,Zepto_Data!$A$2:$A$3732,$B$11,Zepto_Data!$L$2:$L$3732,$B$12,Zepto_Data!$K$2:$K$3732,$B$13,Zepto_Data!$M$2:$M$3732,$B$14),0)))) | H27: =IF(OR($B27="",H$18=""),"",IF($B$6="Count",COUNTIFS(INDEX(ZPD,0,$B$3),$B27,INDEX(ZPD,0,$B$8),H$18,Zepto_Data!$A$2:$A$3732,$B$11,Zepto_Data!$L$2:$L$3732,$B$12,Zepto_Data!$K$2:$K$3732,$B$13,Zepto_Data!$M$2:$M$3732,$B$14),IF($B$6="Sum",SUMIFS(INDEX(ZPD,0,$B$5),INDEX(ZPD,0,$B$3),$B27,INDEX(ZPD,0,$B$8),H$18,Zepto_Data!$A$2:$A$3732,$B$11,Zepto_Data!$L$2:$L$3732,$B$12,Zepto_Data!$K$2:$K$3732,$B$13,Zepto_Data!$M$2:$M$3732,$B$14),IFERROR(SUMIFS(INDEX(ZPD,0,$B$5),INDEX(ZPD,0,$B$3),$B27,INDEX(ZPD,0,$B$8),H$18,Zepto_Data!$A$2:$A$3732,$B$11,Zepto_Data!$L$2:$L$3732,$B$12,Zepto_Data!$K$2:$K$3732,$B$13,Zepto_Data!$M$2:$M$3732,$B$14)/COUNTIFS(INDEX(ZPD,0,$B$3),$B27,INDEX(ZPD,0,$B$8),H$18,Zepto_Data!$A$2:$A$3732,$B$11,Zepto_Data!$L$2:$L$3732,$B$12,Zepto_Data!$K$2:$K$3732,$B$13,Zepto_Data!$M$2:$M$3732,$B$14),0)))) | I27: =IF(OR($B27="",I$18=""),"",IF($B$6="Count",COUNTIFS(INDEX(ZPD,0,$B$3),$B27,INDEX(ZPD,0,$B$8),I$18,Zepto_Data!$A$2:$A$3732,$B$11,Zepto_Data!$L$2:$L$3732,$B$12,Zepto_Data!$K$2:$K$3732,$B$13,Zepto_Data!$M$2:$M$3732,$B$14),IF($B$6="Sum",SUMIFS(INDEX(ZPD,0,$B$5),INDEX(ZPD,0,$B$3),$B27,INDEX(ZPD,0,$B$8),I$18,Zepto_Data!$A$2:$A$3732,$B$11,Zepto_Data!$L$2:$L$3732,$B$12,Zepto_Data!$K$2:$K$3732,$B$13,Zepto_Data!$M$2:$M$3732,$B$14),IFERROR(SUMIFS(INDEX(ZPD,0,$B$5),INDEX(ZPD,0,$B$3),$B27,INDEX(ZPD,0,$B$8),I$18,Zepto_Data!$A$2:$A$3732,$B$11,Zepto_Data!$L$2:$L$3732,$B$12,Zepto_Data!$K$2:$K$3732,$B$13,Zepto_Data!$M$2:$M$3732,$B$14)/COUNTIFS(INDEX(ZPD,0,$B$3),$B27,INDEX(ZPD,0,$B$8),I$18,Zepto_Data!$A$2:$A$3732,$B$11,Zepto_Data!$L$2:$L$3732,$B$12,Zepto_Data!$K$2:$K$3732,$B$13,Zepto_Data!$M$2:$M$3732,$B$14),0)))) | J27: =IF(OR($B27="",J$18=""),"",IF($B$6="Count",COUNTIFS(INDEX(ZPD,0,$B$3),$B27,INDEX(ZPD,0,$B$8),J$18,Zepto_Data!$A$2:$A$3732,$B$11,Zepto_Data!$L$2:$L$3732,$B$12,Zepto_Data!$K$2:$K$3732,$B$13,Zepto_Data!$M$2:$M$3732,$B$14),IF($B$6="Sum",SUMIFS(INDEX(ZPD,0,$B$5),INDEX(ZPD,0,$B$3),$B27,INDEX(ZPD,0,$B$8),J$18,Zepto_Data!$A$2:$A$3732,$B$11,Zepto_Data!$L$2:$L$3732,$B$12,Zepto_Data!$K$2:$K$3732,$B$13,Zepto_Data!$M$2:$M$3732,$B$14),IFERROR(SUMIFS(INDEX(ZPD,0,$B$5),INDEX(ZPD,0,$B$3),$B27,INDEX(ZPD,0,$B$8),J$18,Zepto_Data!$A$2:$A$3732,$B$11,Zepto_Data!$L$2:$L$3732,$B$12,Zepto_Data!$K$2:$K$3732,$B$13,Zepto_Data!$M$2:$M$3732,$B$14)/COUNTIFS(INDEX(ZPD,0,$B$3),$B27,INDEX(ZPD,0,$B$8),J$18,Zepto_Data!$A$2:$A$3732,$B$11,Zepto_Data!$L$2:$L$3732,$B$12,Zepto_Data!$K$2:$K$3732,$B$13,Zepto_Data!$M$2:$M$3732,$B$14),0))))
A28: 9 | B28: =IF(INDEX(ZP_Lists!$L$2:$Q$21,A28,$B$2)="","",INDEX(ZP_Lists!$L$2:$Q$21,A28,$B$2)) -> Ice Cream & Desserts | C28: =IF(B28="","",IF($B$6="Count",COUNTIFS(INDEX(ZPD,0,$B$3),B28,Zepto_Data!$A$2:$A$3732,$B$11,Zepto_Data!$L$2:$L$3732,$B$12,Zepto_Data!$K$2:$K$3732,$B$13,Zepto_Data!$M$2:$M$3732,$B$14),IF($B$6="Sum",SUMIFS(INDEX(ZPD,0,$B$5),INDEX(ZPD,0,$B$3),B28,Zepto_Data!$A$2:$A$3732,$B$11,Zepto_Data!$L$2:$L$3732,$B$12,Zepto_Data!$K$2:$K$3732,$B$13,Zepto_Data!$M$2:$M$3732,$B$14),IFERROR(SUMIFS(INDEX(ZPD,0,$B$5),INDEX(ZPD,0,$B$3),B28,Zepto_Data!$A$2:$A$3732,$B$11,Zepto_Data!$L$2:$L$3732,$B$12,Zepto_Data!$K$2:$K$3732,$B$13,Zepto_Data!$M$2:$M$3732,$B$14)/COUNTIFS(INDEX(ZPD,0,$B$3),B28,Zepto_Data!$A$2:$A$3732,$B$11,Zepto_Data!$L$2:$L$3732,$B$12,Zepto_Data!$K$2:$K$3732,$B$13,Zepto_Data!$M$2:$M$3732,$B$14),0)))) -> 224385 | D28: =IF(B28="","",IF($B$10="Natural order",A28,IF($B$10="Value: high to low",SUMPRODUCT(($B$20:$B$39<>"")*($C$20:$C$39>C28))+SUMPRODUCT(($B$20:B28<>"")*($C$20:C28=C28)),SUMPRODUCT(($B$20:$B$39<>"")*($C$20:$C$39<C28))+SUMPRODUCT(($B$20:B28<>"")*($C$20:C28=C28))))) -> 6 | F28: =IF(OR($B28="",F$18=""),"",IF($B$6="Count",COUNTIFS(INDEX(ZPD,0,$B$3),$B28,INDEX(ZPD,0,$B$8),F$18,Zepto_Data!$A$2:$A$3732,$B$11,Zepto_Data!$L$2:$L$3732,$B$12,Zepto_Data!$K$2:$K$3732,$B$13,Zepto_Data!$M$2:$M$3732,$B$14),IF($B$6="Sum",SUMIFS(INDEX(ZPD,0,$B$5),INDEX(ZPD,0,$B$3),$B28,INDEX(ZPD,0,$B$8),F$18,Zepto_Data!$A$2:$A$3732,$B$11,Zepto_Data!$L$2:$L$3732,$B$12,Zepto_Data!$K$2:$K$3732,$B$13,Zepto_Data!$M$2:$M$3732,$B$14),IFERROR(SUMIFS(INDEX(ZPD,0,$B$5),INDEX(ZPD,0,$B$3),$B28,INDEX(ZPD,0,$B$8),F$18,Zepto_Data!$A$2:$A$3732,$B$11,Zepto_Data!$L$2:$L$3732,$B$12,Zepto_Data!$K$2:$K$3732,$B$13,Zepto_Data!$M$2:$M$3732,$B$14)/COUNTIFS(INDEX(ZPD,0,$B$3),$B28,INDEX(ZPD,0,$B$8),F$18,Zepto_Data!$A$2:$A$3732,$B$11,Zepto_Data!$L$2:$L$3732,$B$12,Zepto_Data!$K$2:$K$3732,$B$13,Zepto_Data!$M$2:$M$3732,$B$14),0)))) -> 224385 | G28: =IF(OR($B28="",G$18=""),"",IF($B$6="Count",COUNTIFS(INDEX(ZPD,0,$B$3),$B28,INDEX(ZPD,0,$B$8),G$18,Zepto_Data!$A$2:$A$3732,$B$11,Zepto_Data!$L$2:$L$3732,$B$12,Zepto_Data!$K$2:$K$3732,$B$13,Zepto_Data!$M$2:$M$3732,$B$14),IF($B$6="Sum",SUMIFS(INDEX(ZPD,0,$B$5),INDEX(ZPD,0,$B$3),$B28,INDEX(ZPD,0,$B$8),G$18,Zepto_Data!$A$2:$A$3732,$B$11,Zepto_Data!$L$2:$L$3732,$B$12,Zepto_Data!$K$2:$K$3732,$B$13,Zepto_Data!$M$2:$M$3732,$B$14),IFERROR(SUMIFS(INDEX(ZPD,0,$B$5),INDEX(ZPD,0,$B$3),$B28,INDEX(ZPD,0,$B$8),G$18,Zepto_Data!$A$2:$A$3732,$B$11,Zepto_Data!$L$2:$L$3732,$B$12,Zepto_Data!$K$2:$K$3732,$B$13,Zepto_Data!$M$2:$M$3732,$B$14)/COUNTIFS(INDEX(ZPD,0,$B$3),$B28,INDEX(ZPD,0,$B$8),G$18,Zepto_Data!$A$2:$A$3732,$B$11,Zepto_Data!$L$2:$L$3732,$B$12,Zepto_Data!$K$2:$K$3732,$B$13,Zepto_Data!$M$2:$M$3732,$B$14),0)))) | H28: =IF(OR($B28="",H$18=""),"",IF($B$6="Count",COUNTIFS(INDEX(ZPD,0,$B$3),$B28,INDEX(ZPD,0,$B$8),H$18,Zepto_Data!$A$2:$A$3732,$B$11,Zepto_Data!$L$2:$L$3732,$B$12,Zepto_Data!$K$2:$K$3732,$B$13,Zepto_Data!$M$2:$M$3732,$B$14),IF($B$6="Sum",SUMIFS(INDEX(ZPD,0,$B$5),INDEX(ZPD,0,$B$3),$B28,INDEX(ZPD,0,$B$8),H$18,Zepto_Data!$A$2:$A$3732,$B$11,Zepto_Data!$L$2:$L$3732,$B$12,Zepto_Data!$K$2:$K$3732,$B$13,Zepto_Data!$M$2:$M$3732,$B$14),IFERROR(SUMIFS(INDEX(ZPD,0,$B$5),INDEX(ZPD,0,$B$3),$B28,INDEX(ZPD,0,$B$8),H$18,Zepto_Data!$A$2:$A$3732,$B$11,Zepto_Data!$L$2:$L$3732,$B$12,Zepto_Data!$K$2:$K$3732,$B$13,Zepto_Data!$M$2:$M$3732,$B$14)/COUNTIFS(INDEX(ZPD,0,$B$3),$B28,INDEX(ZPD,0,$B$8),H$18,Zepto_Data!$A$2:$A$3732,$B$11,Zepto_Data!$L$2:$L$3732,$B$12,Zepto_Data!$K$2:$K$3732,$B$13,Zepto_Data!$M$2:$M$3732,$B$14),0)))) | I28: =IF(OR($B28="",I$18=""),"",IF($B$6="Count",COUNTIFS(INDEX(ZPD,0,$B$3),$B28,INDEX(ZPD,0,$B$8),I$18,Zepto_Data!$A$2:$A$3732,$B$11,Zepto_Data!$L$2:$L$3732,$B$12,Zepto_Data!$K$2:$K$3732,$B$13,Zepto_Data!$M$2:$M$3732,$B$14),IF($B$6="Sum",SUMIFS(INDEX(ZPD,0,$B$5),INDEX(ZPD,0,$B$3),$B28,INDEX(ZPD,0,$B$8),I$18,Zepto_Data!$A$2:$A$3732,$B$11,Zepto_Data!$L$2:$L$3732,$B$12,Zepto_Data!$K$2:$K$3732,$B$13,Zepto_Data!$M$2:$M$3732,$B$14),IFERROR(SUMIFS(INDEX(ZPD,0,$B$5),INDEX(ZPD,0,$B$3),$B28,INDEX(ZPD,0,$B$8),I$18,Zepto_Data!$A$2:$A$3732,$B$11,Zepto_Data!$L$2:$L$3732,$B$12,Zepto_Data!$K$2:$K$3732,$B$13,Zepto_Data!$M$2:$M$3732,$B$14)/COUNTIFS(INDEX(ZPD,0,$B$3),$B28,INDEX(ZPD,0,$B$8),I$18,Zepto_Data!$A$2:$A$3732,$B$11,Zepto_Data!$L$2:$L$3732,$B$12,Zepto_Data!$K$2:$K$3732,$B$13,Zepto_Data!$M$2:$M$3732,$B$14),0)))) | J28: =IF(OR($B28="",J$18=""),"",IF($B$6="Count",COUNTIFS(INDEX(ZPD,0,$B$3),$B28,INDEX(ZPD,0,$B$8),J$18,Zepto_Data!$A$2:$A$3732,$B$11,Zepto_Data!$L$2:$L$3732,$B$12,Zepto_Data!$K$2:$K$3732,$B$13,Zepto_Data!$M$2:$M$3732,$B$14),IF($B$6="Sum",SUMIFS(INDEX(ZPD,0,$B$5),INDEX(ZPD,0,$B$3),$B28,INDEX(ZPD,0,$B$8),J$18,Zepto_Data!$A$2:$A$3732,$B$11,Zepto_Data!$L$2:$L$3732,$B$12,Zepto_Data!$K$2:$K$3732,$B$13,Zepto_Data!$M$2:$M$3732,$B$14),IFERROR(SUMIFS(INDEX(ZPD,0,$B$5),INDEX(ZPD,0,$B$3),$B28,INDEX(ZPD,0,$B$8),J$18,Zepto_Data!$A$2:$A$3732,$B$11,Zepto_Data!$L$2:$L$3732,$B$12,Zepto_Data!$K$2:$K$3732,$B$13,Zepto_Data!$M$2:$M$3732,$B$14)/COUNTIFS(INDEX(ZPD,0,$B$3),$B28,INDEX(ZPD,0,$B$8),J$18,Zepto_Data!$A$2:$A$3732,$B$11,Zepto_Data!$L$2:$L$3732,$B$12,Zepto_Data!$K$2:$K$3732,$B$13,Zepto_Data!$M$2:$M$3732,$B$14),0))))
A29: 10 | B29: =IF(INDEX(ZP_Lists!$L$2:$Q$21,A29,$B$2)="","",INDEX(ZP_Lists!$L$2:$Q$21,A29,$B$2)) -> Meats, Fish & Eggs | C29: =IF(B29="","",IF($B$6="Count",COUNTIFS(INDEX(ZPD,0,$B$3),B29,Zepto_Data!$A$2:$A$3732,$B$11,Zepto_Data!$L$2:$L$3732,$B$12,Zepto_Data!$K$2:$K$3732,$B$13,Zepto_Data!$M$2:$M$3732,$B$14),IF($B$6="Sum",SUMIFS(INDEX(ZPD,0,$B$5),INDEX(ZPD,0,$B$3),B29,Zepto_Data!$A$2:$A$3732,$B$11,Zepto_Data!$L$2:$L$3732,$B$12,Zepto_Data!$K$2:$K$3732,$B$13,Zepto_Data!$M$2:$M$3732,$B$14),IFERROR(SUMIFS(INDEX(ZPD,0,$B$5),INDEX(ZPD,0,$B$3),B29,Zepto_Data!$A$2:$A$3732,$B$11,Zepto_Data!$L$2:$L$3732,$B$12,Zepto_Data!$K$2:$K$3732,$B$13,Zepto_Data!$M$2:$M$3732,$B$14)/COUNTIFS(INDEX(ZPD,0,$B$3),B29,Zepto_Data!$A$2:$A$3732,$B$11,Zepto_Data!$L$2:$L$3732,$B$12,Zepto_Data!$K$2:$K$3732,$B$13,Zepto_Data!$M$2:$M$3732,$B$14),0)))) -> 20693 | D29: =IF(B29="","",IF($B$10="Natural order",A29,IF($B$10="Value: high to low",SUMPRODUCT(($B$20:$B$39<>"")*($C$20:$C$39>C29))+SUMPRODUCT(($B$20:B29<>"")*($C$20:C29=C29)),SUMPRODUCT(($B$20:$B$39<>"")*($C$20:$C$39<C29))+SUMPRODUCT(($B$20:B29<>"")*($C$20:C29=C29))))) -> 13 | F29: =IF(OR($B29="",F$18=""),"",IF($B$6="Count",COUNTIFS(INDEX(ZPD,0,$B$3),$B29,INDEX(ZPD,0,$B$8),F$18,Zepto_Data!$A$2:$A$3732,$B$11,Zepto_Data!$L$2:$L$3732,$B$12,Zepto_Data!$K$2:$K$3732,$B$13,Zepto_Data!$M$2:$M$3732,$B$14),IF($B$6="Sum",SUMIFS(INDEX(ZPD,0,$B$5),INDEX(ZPD,0,$B$3),$B29,INDEX(ZPD,0,$B$8),F$18,Zepto_Data!$A$2:$A$3732,$B$11,Zepto_Data!$L$2:$L$3732,$B$12,Zepto_Data!$K$2:$K$3732,$B$13,Zepto_Data!$M$2:$M$3732,$B$14),IFERROR(SUMIFS(INDEX(ZPD,0,$B$5),INDEX(ZPD,0,$B$3),$B29,INDEX(ZPD,0,$B$8),F$18,Zepto_Data!$A$2:$A$3732,$B$11,Zepto_Data!$L$2:$L$3732,$B$12,Zepto_Data!$K$2:$K$3732,$B$13,Zepto_Data!$M$2:$M$3732,$B$14)/COUNTIFS(INDEX(ZPD,0,$B$3),$B29,INDEX(ZPD,0,$B$8),F$18,Zepto_Data!$A$2:$A$3732,$B$11,Zepto_Data!$L$2:$L$3732,$B$12,Zepto_Data!$K$2:$K$3732,$B$13,Zepto_Data!$M$2:$M$3732,$B$14),0)))) -> 20693 | G29: =IF(OR($B29="",G$18=""),"",IF($B$6="Count",COUNTIFS(INDEX(ZPD,0,$B$3),$B29,INDEX(ZPD,0,$B$8),G$18,Zepto_Data!$A$2:$A$3732,$B$11,Zepto_Data!$L$2:$L$3732,$B$12,Zepto_Data!$K$2:$K$3732,$B$13,Zepto_Data!$M$2:$M$3732,$B$14),IF($B$6="Sum",SUMIFS(INDEX(ZPD,0,$B$5),INDEX(ZPD,0,$B$3),$B29,INDEX(ZPD,0,$B$8),G$18,Zepto_Data!$A$2:$A$3732,$B$11,Zepto_Data!$L$2:$L$3732,$B$12,Zepto_Data!$K$2:$K$3732,$B$13,Zepto_Data!$M$2:$M$3732,$B$14),IFERROR(SUMIFS(INDEX(ZPD,0,$B$5),INDEX(ZPD,0,$B$3),$B29,INDEX(ZPD,0,$B$8),G$18,Zepto_Data!$A$2:$A$3732,$B$11,Zepto_Data!$L$2:$L$3732,$B$12,Zepto_Data!$K$2:$K$3732,$B$13,Zepto_Data!$M$2:$M$3732,$B$14)/COUNTIFS(INDEX(ZPD,0,$B$3),$B29,INDEX(ZPD,0,$B$8),G$18,Zepto_Data!$A$2:$A$3732,$B$11,Zepto_Data!$L$2:$L$3732,$B$12,Zepto_Data!$K$2:$K$3732,$B$13,Zepto_Data!$M$2:$M$3732,$B$14),0)))) | H29: =IF(OR($B29="",H$18=""),"",IF($B$6="Count",COUNTIFS(INDEX(ZPD,0,$B$3),$B29,INDEX(ZPD,0,$B$8),H$18,Zepto_Data!$A$2:$A$3732,$B$11,Zepto_Data!$L$2:$L$3732,$B$12,Zepto_Data!$K$2:$K$3732,$B$13,Zepto_Data!$M$2:$M$3732,$B$14),IF($B$6="Sum",SUMIFS(INDEX(ZPD,0,$B$5),INDEX(ZPD,0,$B$3),$B29,INDEX(ZPD,0,$B$8),H$18,Zepto_Data!$A$2:$A$3732,$B$11,Zepto_Data!$L$2:$L$3732,$B$12,Zepto_Data!$K$2:$K$3732,$B$13,Zepto_Data!$M$2:$M$3732,$B$14),IFERROR(SUMIFS(INDEX(ZPD,0,$B$5),INDEX(ZPD,0,$B$3),$B29,INDEX(ZPD,0,$B$8),H$18,Zepto_Data!$A$2:$A$3732,$B$11,Zepto_Data!$L$2:$L$3732,$B$12,Zepto_Data!$K$2:$K$3732,$B$13,Zepto_Data!$M$2:$M$3732,$B$14)/COUNTIFS(INDEX(ZPD,0,$B$3),$B29,INDEX(ZPD,0,$B$8),H$18,Zepto_Data!$A$2:$A$3732,$B$11,Zepto_Data!$L$2:$L$3732,$B$12,Zepto_Data!$K$2:$K$3732,$B$13,Zepto_Data!$M$2:$M$3732,$B$14),0)))) | I29: =IF(OR($B29="",I$18=""),"",IF($B$6="Count",COUNTIFS(INDEX(ZPD,0,$B$3),$B29,INDEX(ZPD,0,$B$8),I$18,Zepto_Data!$A$2:$A$3732,$B$11,Zepto_Data!$L$2:$L$3732,$B$12,Zepto_Data!$K$2:$K$3732,$B$13,Zepto_Data!$M$2:$M$3732,$B$14),IF($B$6="Sum",SUMIFS(INDEX(ZPD,0,$B$5),INDEX(ZPD,0,$B$3),$B29,INDEX(ZPD,0,$B$8),I$18,Zepto_Data!$A$2:$A$3732,$B$11,Zepto_Data!$L$2:$L$3732,$B$12,Zepto_Data!$K$2:$K$3732,$B$13,Zepto_Data!$M$2:$M$3732,$B$14),IFERROR(SUMIFS(INDEX(ZPD,0,$B$5),INDEX(ZPD,0,$B$3),$B29,INDEX(ZPD,0,$B$8),I$18,Zepto_Data!$A$2:$A$3732,$B$11,Zepto_Data!$L$2:$L$3732,$B$12,Zepto_Data!$K$2:$K$3732,$B$13,Zepto_Data!$M$2:$M$3732,$B$14)/COUNTIFS(INDEX(ZPD,0,$B$3),$B29,INDEX(ZPD,0,$B$8),I$18,Zepto_Data!$A$2:$A$3732,$B$11,Zepto_Data!$L$2:$L$3732,$B$12,Zepto_Data!$K$2:$K$3732,$B$13,Zepto_Data!$M$2:$M$3732,$B$14),0)))) | J29: =IF(OR($B29="",J$18=""),"",IF($B$6="Count",COUNTIFS(INDEX(ZPD,0,$B$3),$B29,INDEX(ZPD,0,$B$8),J$18,Zepto_Data!$A$2:$A$3732,$B$11,Zepto_Data!$L$2:$L$3732,$B$12,Zepto_Data!$K$2:$K$3732,$B$13,Zepto_Data!$M$2:$M$3732,$B$14),IF($B$6="Sum",SUMIFS(INDEX(ZPD,0,$B$5),INDEX(ZPD,0,$B$3),$B29,INDEX(ZPD,0,$B$8),J$18,Zepto_Data!$A$2:$A$3732,$B$11,Zepto_Data!$L$2:$L$3732,$B$12,Zepto_Data!$K$2:$K$3732,$B$13,Zepto_Data!$M$2:$M$3732,$B$14),IFERROR(SUMIFS(INDEX(ZPD,0,$B$5),INDEX(ZPD,0,$B$3),$B29,INDEX(ZPD,0,$B$8),J$18,Zepto_Data!$A$2:$A$3732,$B$11,Zepto_Data!$L$2:$L$3732,$B$12,Zepto_Data!$K$2:$K$3732,$B$13,Zepto_Data!$M$2:$M$3732,$B$14)/COUNTIFS(INDEX(ZPD,0,$B$3),$B29,INDEX(ZPD,0,$B$8),J$18,Zepto_Data!$A$2:$A$3732,$B$11,Zepto_Data!$L$2:$L$3732,$B$12,Zepto_Data!$K$2:$K$3732,$B$13,Zepto_Data!$M$2:$M$3732,$B$14),0))))
A30: 11 | B30: =IF(INDEX(ZP_Lists!$L$2:$Q$21,A30,$B$2)="","",INDEX(ZP_Lists!$L$2:$Q$21,A30,$B$2)) -> Munchies | C30: =IF(B30="","",IF($B$6="Count",COUNTIFS(INDEX(ZPD,0,$B$3),B30,Zepto_Data!$A$2:$A$3732,$B$11,Zepto_Data!$L$2:$L$3732,$B$12,Zepto_Data!$K$2:$K$3732,$B$13,Zepto_Data!$M$2:$M$3732,$B$14),IF($B$6="Sum",SUMIFS(INDEX(ZPD,0,$B$5),INDEX(ZPD,0,$B$3),B30,Zepto_Data!$A$2:$A$3732,$B$11,Zepto_Data!$L$2:$L$3732,$B$12,Zepto_Data!$K$2:$K$3732,$B$13,Zepto_Data!$M$2:$M$3732,$B$14),IFERROR(SUMIFS(INDEX(ZPD,0,$B$5),INDEX(ZPD,0,$B$3),B30,Zepto_Data!$A$2:$A$3732,$B$11,Zepto_Data!$L$2:$L$3732,$B$12,Zepto_Data!$K$2:$K$3732,$B$13,Zepto_Data!$M$2:$M$3732,$B$14)/COUNTIFS(INDEX(ZPD,0,$B$3),B30,Zepto_Data!$A$2:$A$3732,$B$11,Zepto_Data!$L$2:$L$3732,$B$12,Zepto_Data!$K$2:$K$3732,$B$13,Zepto_Data!$M$2:$M$3732,$B$14),0)))) -> 337369 | D30: =IF(B30="","",IF($B$10="Natural order",A30,IF($B$10="Value: high to low",SUMPRODUCT(($B$20:$B$39<>"")*($C$20:$C$39>C30))+SUMPRODUCT(($B$20:B30<>"")*($C$20:C30=C30)),SUMPRODUCT(($B$20:$B$39<>"")*($C$20:$C$39<C30))+SUMPRODUCT(($B$20:B30<>"")*($C$20:C30=C30))))) -> 2 | F30: =IF(OR($B30="",F$18=""),"",IF($B$6="Count",COUNTIFS(INDEX(ZPD,0,$B$3),$B30,INDEX(ZPD,0,$B$8),F$18,Zepto_Data!$A$2:$A$3732,$B$11,Zepto_Data!$L$2:$L$3732,$B$12,Zepto_Data!$K$2:$K$3732,$B$13,Zepto_Data!$M$2:$M$3732,$B$14),IF($B$6="Sum",SUMIFS(INDEX(ZPD,0,$B$5),INDEX(ZPD,0,$B$3),$B30,INDEX(ZPD,0,$B$8),F$18,Zepto_Data!$A$2:$A$3732,$B$11,Zepto_Data!$L$2:$L$3732,$B$12,Zepto_Data!$K$2:$K$3732,$B$13,Zepto_Data!$M$2:$M$3732,$B$14),IFERROR(SUMIFS(INDEX(ZPD,0,$B$5),INDEX(ZPD,0,$B$3),$B30,INDEX(ZPD,0,$B$8),F$18,Zepto_Data!$A$2:$A$3732,$B$11,Zepto_Data!$L$2:$L$3732,$B$12,Zepto_Data!$K$2:$K$3732,$B$13,Zepto_Data!$M$2:$M$3732,$B$14)/COUNTIFS(INDEX(ZPD,0,$B$3),$B30,INDEX(ZPD,0,$B$8),F$18,Zepto_Data!$A$2:$A$3732,$B$11,Zepto_Data!$L$2:$L$3732,$B$12,Zepto_Data!$K$2:$K$3732,$B$13,Zepto_Data!$M$2:$M$3732,$B$14),0)))) -> 337369 | G30: =IF(OR($B30="",G$18=""),"",IF($B$6="Count",COUNTIFS(INDEX(ZPD,0,$B$3),$B30,INDEX(ZPD,0,$B$8),G$18,Zepto_Data!$A$2:$A$3732,$B$11,Zepto_Data!$L$2:$L$3732,$B$12,Zepto_Data!$K$2:$K$3732,$B$13,Zepto_Data!$M$2:$M$3732,$B$14),IF($B$6="Sum",SUMIFS(INDEX(ZPD,0,$B$5),INDEX(ZPD,0,$B$3),$B30,INDEX(ZPD,0,$B$8),G$18,Zepto_Data!$A$2:$A$3732,$B$11,Zepto_Data!$L$2:$L$3732,$B$12,Zepto_Data!$K$2:$K$3732,$B$13,Zepto_Data!$M$2:$M$3732,$B$14),IFERROR(SUMIFS(INDEX(ZPD,0,$B$5),INDEX(ZPD,0,$B$3),$B30,INDEX(ZPD,0,$B$8),G$18,Zepto_Data!$A$2:$A$3732,$B$11,Zepto_Data!$L$2:$L$3732,$B$12,Zepto_Data!$K$2:$K$3732,$B$13,Zepto_Data!$M$2:$M$3732,$B$14)/COUNTIFS(INDEX(ZPD,0,$B$3),$B30,INDEX(ZPD,0,$B$8),G$18,Zepto_Data!$A$2:$A$3732,$B$11,Zepto_Data!$L$2:$L$3732,$B$12,Zepto_Data!$K$2:$K$3732,$B$13,Zepto_Data!$M$2:$M$3732,$B$14),0)))) | H30: =IF(OR($B30="",H$18=""),"",IF($B$6="Count",COUNTIFS(INDEX(ZPD,0,$B$3),$B30,INDEX(ZPD,0,$B$8),H$18,Zepto_Data!$A$2:$A$3732,$B$11,Zepto_Data!$L$2:$L$3732,$B$12,Zepto_Data!$K$2:$K$3732,$B$13,Zepto_Data!$M$2:$M$3732,$B$14),IF($B$6="Sum",SUMIFS(INDEX(ZPD,0,$B$5),INDEX(ZPD,0,$B$3),$B30,INDEX(ZPD,0,$B$8),H$18,Zepto_Data!$A$2:$A$3732,$B$11,Zepto_Data!$L$2:$L$3732,$B$12,Zepto_Data!$K$2:$K$3732,$B$13,Zepto_Data!$M$2:$M$3732,$B$14),IFERROR(SUMIFS(INDEX(ZPD,0,$B$5),INDEX(ZPD,0,$B$3),$B30,INDEX(ZPD,0,$B$8),H$18,Zepto_Data!$A$2:$A$3732,$B$11,Zepto_Data!$L$2:$L$3732,$B$12,Zepto_Data!$K$2:$K$3732,$B$13,Zepto_Data!$M$2:$M$3732,$B$14)/COUNTIFS(INDEX(ZPD,0,$B$3),$B30,INDEX(ZPD,0,$B$8),H$18,Zepto_Data!$A$2:$A$3732,$B$11,Zepto_Data!$L$2:$L$3732,$B$12,Zepto_Data!$K$2:$K$3732,$B$13,Zepto_Data!$M$2:$M$3732,$B$14),0)))) | I30: =IF(OR($B30="",I$18=""),"",IF($B$6="Count",COUNTIFS(INDEX(ZPD,0,$B$3),$B30,INDEX(ZPD,0,$B$8),I$18,Zepto_Data!$A$2:$A$3732,$B$11,Zepto_Data!$L$2:$L$3732,$B$12,Zepto_Data!$K$2:$K$3732,$B$13,Zepto_Data!$M$2:$M$3732,$B$14),IF($B$6="Sum",SUMIFS(INDEX(ZPD,0,$B$5),INDEX(ZPD,0,$B$3),$B30,INDEX(ZPD,0,$B$8),I$18,Zepto_Data!$A$2:$A$3732,$B$11,Zepto_Data!$L$2:$L$3732,$B$12,Zepto_Data!$K$2:$K$3732,$B$13,Zepto_Data!$M$2:$M$3732,$B$14),IFERROR(SUMIFS(INDEX(ZPD,0,$B$5),INDEX(ZPD,0,$B$3),$B30,INDEX(ZPD,0,$B$8),I$18,Zepto_Data!$A$2:$A$3732,$B$11,Zepto_Data!$L$2:$L$3732,$B$12,Zepto_Data!$K$2:$K$3732,$B$13,Zepto_Data!$M$2:$M$3732,$B$14)/COUNTIFS(INDEX(ZPD,0,$B$3),$B30,INDEX(ZPD,0,$B$8),I$18,Zepto_Data!$A$2:$A$3732,$B$11,Zepto_Data!$L$2:$L$3732,$B$12,Zepto_Data!$K$2:$K$3732,$B$13,Zepto_Data!$M$2:$M$3732,$B$14),0)))) | J30: =IF(OR($B30="",J$18=""),"",IF($B$6="Count",COUNTIFS(INDEX(ZPD,0,$B$3),$B30,INDEX(ZPD,0,$B$8),J$18,Zepto_Data!$A$2:$A$3732,$B$11,Zepto_Data!$L$2:$L$3732,$B$12,Zepto_Data!$K$2:$K$3732,$B$13,Zepto_Data!$M$2:$M$3732,$B$14),IF($B$6="Sum",SUMIFS(INDEX(ZPD,0,$B$5),INDEX(ZPD,0,$B$3),$B30,INDEX(ZPD,0,$B$8),J$18,Zepto_Data!$A$2:$A$3732,$B$11,Zepto_Data!$L$2:$L$3732,$B$12,Zepto_Data!$K$2:$K$3732,$B$13,Zepto_Data!$M$2:$M$3732,$B$14),IFERROR(SUMIFS(INDEX(ZPD,0,$B$5),INDEX(ZPD,0,$B$3),$B30,INDEX(ZPD,0,$B$8),J$18,Zepto_Data!$A$2:$A$3732,$B$11,Zepto_Data!$L$2:$L$3732,$B$12,Zepto_Data!$K$2:$K$3732,$B$13,Zepto_Data!$M$2:$M$3732,$B$14)/COUNTIFS(INDEX(ZPD,0,$B$3),$B30,INDEX(ZPD,0,$B$8),J$18,Zepto_Data!$A$2:$A$3732,$B$11,Zepto_Data!$L$2:$L$3732,$B$12,Zepto_Data!$K$2:$K$3732,$B$13,Zepto_Data!$M$2:$M$3732,$B$14),0))))
A31: 12 | B31: =IF(INDEX(ZP_Lists!$L$2:$Q$21,A31,$B$2)="","",INDEX(ZP_Lists!$L$2:$Q$21,A31,$B$2)) -> Paan Corner | C31: =IF(B31="","",IF($B$6="Count",COUNTIFS(INDEX(ZPD,0,$B$3),B31,Zepto_Data!$A$2:$A$3732,$B$11,Zepto_Data!$L$2:$L$3732,$B$12,Zepto_Data!$K$2:$K$3732,$B$13,Zepto_Data!$M$2:$M$3732,$B$14),IF($B$6="Sum",SUMIFS(INDEX(ZPD,0,$B$5),INDEX(ZPD,0,$B$3),B31,Zepto_Data!$A$2:$A$3732,$B$11,Zepto_Data!$L$2:$L$3732,$B$12,Zepto_Data!$K$2:$K$3732,$B$13,Zepto_Data!$M$2:$M$3732,$B$14),IFERROR(SUMIFS(INDEX(ZPD,0,$B$5),INDEX(ZPD,0,$B$3),B31,Zepto_Data!$A$2:$A$3732,$B$11,Zepto_Data!$L$2:$L$3732,$B$12,Zepto_Data!$K$2:$K$3732,$B$13,Zepto_Data!$M$2:$M$3732,$B$14)/COUNTIFS(INDEX(ZPD,0,$B$3),B31,Zepto_Data!$A$2:$A$3732,$B$11,Zepto_Data!$L$2:$L$3732,$B$12,Zepto_Data!$K$2:$K$3732,$B$13,Zepto_Data!$M$2:$M$3732,$B$14),0)))) -> 270849 | D31: =IF(B31="","",IF($B$10="Natural order",A31,IF($B$10="Value: high to low",SUMPRODUCT(($B$20:$B$39<>"")*($C$20:$C$39>C31))+SUMPRODUCT(($B$20:B31<>"")*($C$20:C31=C31)),SUMPRODUCT(($B$20:$B$39<>"")*($C$20:$C$39<C31))+SUMPRODUCT(($B$20:B31<>"")*($C$20:C31=C31))))) -> 3 | F31: =IF(OR($B31="",F$18=""),"",IF($B$6="Count",COUNTIFS(INDEX(ZPD,0,$B$3),$B31,INDEX(ZPD,0,$B$8),F$18,Zepto_Data!$A$2:$A$3732,$B$11,Zepto_Data!$L$2:$L$3732,$B$12,Zepto_Data!$K$2:$K$3732,$B$13,Zepto_Data!$M$2:$M$3732,$B$14),IF($B$6="Sum",SUMIFS(INDEX(ZPD,0,$B$5),INDEX(ZPD,0,$B$3),$B31,INDEX(ZPD,0,$B$8),F$18,Zepto_Data!$A$2:$A$3732,$B$11,Zepto_Data!$L$2:$L$3732,$B$12,Zepto_Data!$K$2:$K$3732,$B$13,Zepto_Data!$M$2:$M$3732,$B$14),IFERROR(SUMIFS(INDEX(ZPD,0,$B$5),INDEX(ZPD,0,$B$3),$B31,INDEX(ZPD,0,$B$8),F$18,Zepto_Data!$A$2:$A$3732,$B$11,Zepto_Data!$L$2:$L$3732,$B$12,Zepto_Data!$K$2:$K$3732,$B$13,Zepto_Data!$M$2:$M$3732,$B$14)/COUNTIFS(INDEX(ZPD,0,$B$3),$B31,INDEX(ZPD,0,$B$8),F$18,Zepto_Data!$A$2:$A$3732,$B$11,Zepto_Data!$L$2:$L$3732,$B$12,Zepto_Data!$K$2:$K$3732,$B$13,Zepto_Data!$M$2:$M$3732,$B$14),0)))) -> 270849 | G31: =IF(OR($B31="",G$18=""),"",IF($B$6="Count",COUNTIFS(INDEX(ZPD,0,$B$3),$B31,INDEX(ZPD,0,$B$8),G$18,Zepto_Data!$A$2:$A$3732,$B$11,Zepto_Data!$L$2:$L$3732,$B$12,Zepto_Data!$K$2:$K$3732,$B$13,Zepto_Data!$M$2:$M$3732,$B$14),IF($B$6="Sum",SUMIFS(INDEX(ZPD,0,$B$5),INDEX(ZPD,0,$B$3),$B31,INDEX(ZPD,0,$B$8),G$18,Zepto_Data!$A$2:$A$3732,$B$11,Zepto_Data!$L$2:$L$3732,$B$12,Zepto_Data!$K$2:$K$3732,$B$13,Zepto_Data!$M$2:$M$3732,$B$14),IFERROR(SUMIFS(INDEX(ZPD,0,$B$5),INDEX(ZPD,0,$B$3),$B31,INDEX(ZPD,0,$B$8),G$18,Zepto_Data!$A$2:$A$3732,$B$11,Zepto_Data!$L$2:$L$3732,$B$12,Zepto_Data!$K$2:$K$3732,$B$13,Zepto_Data!$M$2:$M$3732,$B$14)/COUNTIFS(INDEX(ZPD,0,$B$3),$B31,INDEX(ZPD,0,$B$8),G$18,Zepto_Data!$A$2:$A$3732,$B$11,Zepto_Data!$L$2:$L$3732,$B$12,Zepto_Data!$K$2:$K$3732,$B$13,Zepto_Data!$M$2:$M$3732,$B$14),0)))) | H31: =IF(OR($B31="",H$18=""),"",IF($B$6="Count",COUNTIFS(INDEX(ZPD,0,$B$3),$B31,INDEX(ZPD,0,$B$8),H$18,Zepto_Data!$A$2:$A$3732,$B$11,Zepto_Data!$L$2:$L$3732,$B$12,Zepto_Data!$K$2:$K$3732,$B$13,Zepto_Data!$M$2:$M$3732,$B$14),IF($B$6="Sum",SUMIFS(INDEX(ZPD,0,$B$5),INDEX(ZPD,0,$B$3),$B31,INDEX(ZPD,0,$B$8),H$18,Zepto_Data!$A$2:$A$3732,$B$11,Zepto_Data!$L$2:$L$3732,$B$12,Zepto_Data!$K$2:$K$3732,$B$13,Zepto_Data!$M$2:$M$3732,$B$14),IFERROR(SUMIFS(INDEX(ZPD,0,$B$5),INDEX(ZPD,0,$B$3),$B31,INDEX(ZPD,0,$B$8),H$18,Zepto_Data!$A$2:$A$3732,$B$11,Zepto_Data!$L$2:$L$3732,$B$12,Zepto_Data!$K$2:$K$3732,$B$13,Zepto_Data!$M$2:$M$3732,$B$14)/COUNTIFS(INDEX(ZPD,0,$B$3),$B31,INDEX(ZPD,0,$B$8),H$18,Zepto_Data!$A$2:$A$3732,$B$11,Zepto_Data!$L$2:$L$3732,$B$12,Zepto_Data!$K$2:$K$3732,$B$13,Zepto_Data!$M$2:$M$3732,$B$14),0)))) | I31: =IF(OR($B31="",I$18=""),"",IF($B$6="Count",COUNTIFS(INDEX(ZPD,0,$B$3),$B31,INDEX(ZPD,0,$B$8),I$18,Zepto_Data!$A$2:$A$3732,$B$11,Zepto_Data!$L$2:$L$3732,$B$12,Zepto_Data!$K$2:$K$3732,$B$13,Zepto_Data!$M$2:$M$3732,$B$14),IF($B$6="Sum",SUMIFS(INDEX(ZPD,0,$B$5),INDEX(ZPD,0,$B$3),$B31,INDEX(ZPD,0,$B$8),I$18,Zepto_Data!$A$2:$A$3732,$B$11,Zepto_Data!$L$2:$L$3732,$B$12,Zepto_Data!$K$2:$K$3732,$B$13,Zepto_Data!$M$2:$M$3732,$B$14),IFERROR(SUMIFS(INDEX(ZPD,0,$B$5),INDEX(ZPD,0,$B$3),$B31,INDEX(ZPD,0,$B$8),I$18,Zepto_Data!$A$2:$A$3732,$B$11,Zepto_Data!$L$2:$L$3732,$B$12,Zepto_Data!$K$2:$K$3732,$B$13,Zepto_Data!$M$2:$M$3732,$B$14)/COUNTIFS(INDEX(ZPD,0,$B$3),$B31,INDEX(ZPD,0,$B$8),I$18,Zepto_Data!$A$2:$A$3732,$B$11,Zepto_Data!$L$2:$L$3732,$B$12,Zepto_Data!$K$2:$K$3732,$B$13,Zepto_Data!$M$2:$M$3732,$B$14),0)))) | J31: =IF(OR($B31="",J$18=""),"",IF($B$6="Count",COUNTIFS(INDEX(ZPD,0,$B$3),$B31,INDEX(ZPD,0,$B$8),J$18,Zepto_Data!$A$2:$A$3732,$B$11,Zepto_Data!$L$2:$L$3732,$B$12,Zepto_Data!$K$2:$K$3732,$B$13,Zepto_Data!$M$2:$M$3732,$B$14),IF($B$6="Sum",SUMIFS(INDEX(ZPD,0,$B$5),INDEX(ZPD,0,$B$3),$B31,INDEX(ZPD,0,$B$8),J$18,Zepto_Data!$A$2:$A$3732,$B$11,Zepto_Data!$L$2:$L$3732,$B$12,Zepto_Data!$K$2:$K$3732,$B$13,Zepto_Data!$M$2:$M$3732,$B$14),IFERROR(SUMIFS(INDEX(ZPD,0,$B$5),INDEX(ZPD,0,$B$3),$B31,INDEX(ZPD,0,$B$8),J$18,Zepto_Data!$A$2:$A$3732,$B$11,Zepto_Data!$L$2:$L$3732,$B$12,Zepto_Data!$K$2:$K$3732,$B$13,Zepto_Data!$M$2:$M$3732,$B$14)/COUNTIFS(INDEX(ZPD,0,$B$3),$B31,INDEX(ZPD,0,$B$8),J$18,Zepto_Data!$A$2:$A$3732,$B$11,Zepto_Data!$L$2:$L$3732,$B$12,Zepto_Data!$K$2:$K$3732,$B$13,Zepto_Data!$M$2:$M$3732,$B$14),0))))
... A39: 20 | B39: =IF(INDEX(ZP_Lists!$L$2:$Q$21,A39,$B$2)="","",INDEX(ZP_Lists!$L$2:$Q$21,A39,$B$2)) | C39: =IF(B39="","",IF($B$6="Count",COUNTIFS(INDEX(ZPD,0,$B$3),B39,Zepto_Data!$A$2:$A$3732,$B$11,Zepto_Data!$L$2:$L$3732,$B$12,Zepto_Data!$K$2:$K$3732,$B$13,Zepto_Data!$M$2:$M$3732,$B$14),IF($B$6="Sum",SUMIFS(INDEX(ZPD,0,$B$5),INDEX(ZPD,0,$B$3),B39,Zepto_Data!$A$2:$A$3732,$B$11,Zepto_Data!$L$2:$L$3732,$B$12,Zepto_Data!$K$2:$K$3732,$B$13,Zepto_Data!$M$2:$M$3732,$B$14),IFERROR(SUMIFS(INDEX(ZPD,0,$B$5),INDEX(ZPD,0,$B$3),B39,Zepto_Data!$A$2:$A$3732,$B$11,Zepto_Data!$L$2:$L$3732,$B$12,Zepto_Data!$K$2:$K$3732,$B$13,Zepto_Data!$M$2:$M$3732,$B$14)/COUNTIFS(INDEX(ZPD,0,$B$3),B39,Zepto_Data!$A$2:$A$3732,$B$11,Zepto_Data!$L$2:$L$3732,$B$12,Zepto_Data!$K$2:$K$3732,$B$13,Zepto_Data!$M$2:$M$3732,$B$14),0)))) | D39: =IF(B39="","",IF($B$10="Natural order",A39,IF($B$10="Value: high to low",SUMPRODUCT(($B$20:$B$39<>"")*($C$20:$C$39>C39))+SUMPRODUCT(($B$20:B39<>"")*($C$20:C39=C39)),SUMPRODUCT(($B$20:$B$39<>"")*($C$20:$C$39<C39))+SUMPRODUCT(($B$20:B39<>"")*($C$20:C39=C39))))) | F39: =IF(OR($B39="",F$18=""),"",IF($B$6="Count",COUNTIFS(INDEX(ZPD,0,$B$3),$B39,INDEX(ZPD,0,$B$8),F$18,Zepto_Data!$A$2:$A$3732,$B$11,Zepto_Data!$L$2:$L$3732,$B$12,Zepto_Data!$K$2:$K$3732,$B$13,Zepto_Data!$M$2:$M$3732,$B$14),IF($B$6="Sum",SUMIFS(INDEX(ZPD,0,$B$5),INDEX(ZPD,0,$B$3),$B39,INDEX(ZPD,0,$B$8),F$18,Zepto_Data!$A$2:$A$3732,$B$11,Zepto_Data!$L$2:$L$3732,$B$12,Zepto_Data!$K$2:$K$3732,$B$13,Zepto_Data!$M$2:$M$3732,$B$14),IFERROR(SUMIFS(INDEX(ZPD,0,$B$5),INDEX(ZPD,0,$B$3),$B39,INDEX(ZPD,0,$B$8),F$18,Zepto_Data!$A$2:$A$3732,$B$11,Zepto_Data!$L$2:$L$3732,$B$12,Zepto_Data!$K$2:$K$3732,$B$13,Zepto_Data!$M$2:$M$3732,$B$14)/COUNTIFS(INDEX(ZPD,0,$B$3),$B39,INDEX(ZPD,0,$B$8),F$18,Zepto_Data!$A$2:$A$3732,$B$11,Zepto_Data!$L$2:$L$3732,$B$12,Zepto_Data!$K$2:$K$3732,$B$13,Zepto_Data!$M$2:$M$3732,$B$14),0)))) | G39: =IF(OR($B39="",G$18=""),"",IF($B$6="Count",COUNTIFS(INDEX(ZPD,0,$B$3),$B39,INDEX(ZPD,0,$B$8),G$18,Zepto_Data!$A$2:$A$3732,$B$11,Zepto_Data!$L$2:$L$3732,$B$12,Zepto_Data!$K$2:$K$3732,$B$13,Zepto_Data!$M$2:$M$3732,$B$14),IF($B$6="Sum",SUMIFS(INDEX(ZPD,0,$B$5),INDEX(ZPD,0,$B$3),$B39,INDEX(ZPD,0,$B$8),G$18,Zepto_Data!$A$2:$A$3732,$B$11,Zepto_Data!$L$2:$L$3732,$B$12,Zepto_Data!$K$2:$K$3732,$B$13,Zepto_Data!$M$2:$M$3732,$B$14),IFERROR(SUMIFS(INDEX(ZPD,0,$B$5),INDEX(ZPD,0,$B$3),$B39,INDEX(ZPD,0,$B$8),G$18,Zepto_Data!$A$2:$A$3732,$B$11,Zepto_Data!$L$2:$L$3732,$B$12,Zepto_Data!$K$2:$K$3732,$B$13,Zepto_Data!$M$2:$M$3732,$B$14)/COUNTIFS(INDEX(ZPD,0,$B$3),$B39,INDEX(ZPD,0,$B$8),G$18,Zepto_Data!$A$2:$A$3732,$B$11,Zepto_Data!$L$2:$L$3732,$B$12,Zepto_Data!$K$2:$K$3732,$B$13,Zepto_Data!$M$2:$M$3732,$B$14),0)))) | H39: =IF(OR($B39="",H$18=""),"",IF($B$6="Count",COUNTIFS(INDEX(ZPD,0,$B$3),$B39,INDEX(ZPD,0,$B$8),H$18,Zepto_Data!$A$2:$A$3732,$B$11,Zepto_Data!$L$2:$L$3732,$B$12,Zepto_Data!$K$2:$K$3732,$B$13,Zepto_Data!$M$2:$M$3732,$B$14),IF($B$6="Sum",SUMIFS(INDEX(ZPD,0,$B$5),INDEX(ZPD,0,$B$3),$B39,INDEX(ZPD,0,$B$8),H$18,Zepto_Data!$A$2:$A$3732,$B$11,Zepto_Data!$L$2:$L$3732,$B$12,Zepto_Data!$K$2:$K$3732,$B$13,Zepto_Data!$M$2:$M$3732,$B$14),IFERROR(SUMIFS(INDEX(ZPD,0,$B$5),INDEX(ZPD,0,$B$3),$B39,INDEX(ZPD,0,$B$8),H$18,Zepto_Data!$A$2:$A$3732,$B$11,Zepto_Data!$L$2:$L$3732,$B$12,Zepto_Data!$K$2:$K$3732,$B$13,Zepto_Data!$M$2:$M$3732,$B$14)/COUNTIFS(INDEX(ZPD,0,$B$3),$B39,INDEX(ZPD,0,$B$8),H$18,Zepto_Data!$A$2:$A$3732,$B$11,Zepto_Data!$L$2:$L$3732,$B$12,Zepto_Data!$K$2:$K$3732,$B$13,Zepto_Data!$M$2:$M$3732,$B$14),0)))) | I39: =IF(OR($B39="",I$18=""),"",IF($B$6="Count",COUNTIFS(INDEX(ZPD,0,$B$3),$B39,INDEX(ZPD,0,$B$8),I$18,Zepto_Data!$A$2:$A$3732,$B$11,Zepto_Data!$L$2:$L$3732,$B$12,Zepto_Data!$K$2:$K$3732,$B$13,Zepto_Data!$M$2:$M$3732,$B$14),IF($B$6="Sum",SUMIFS(INDEX(ZPD,0,$B$5),INDEX(ZPD,0,$B$3),$B39,INDEX(ZPD,0,$B$8),I$18,Zepto_Data!$A$2:$A$3732,$B$11,Zepto_Data!$L$2:$L$3732,$B$12,Zepto_Data!$K$2:$K$3732,$B$13,Zepto_Data!$M$2:$M$3732,$B$14),IFERROR(SUMIFS(INDEX(ZPD,0,$B$5),INDEX(ZPD,0,$B$3),$B39,INDEX(ZPD,0,$B$8),I$18,Zepto_Data!$A$2:$A$3732,$B$11,Zepto_Data!$L$2:$L$3732,$B$12,Zepto_Data!$K$2:$K$3732,$B$13,Zepto_Data!$M$2:$M$3732,$B$14)/COUNTIFS(INDEX(ZPD,0,$B$3),$B39,INDEX(ZPD,0,$B$8),I$18,Zepto_Data!$A$2:$A$3732,$B$11,Zepto_Data!$L$2:$L$3732,$B$12,Zepto_Data!$K$2:$K$3732,$B$13,Zepto_Data!$M$2:$M$3732,$B$14),0)))) | J39: =IF(OR($B39="",J$18=""),"",IF($B$6="Count",COUNTIFS(INDEX(ZPD,0,$B$3),$B39,INDEX(ZPD,0,$B$8),J$18,Zepto_Data!$A$2:$A$3732,$B$11,Zepto_Data!$L$2:$L$3732,$B$12,Zepto_Data!$K$2:$K$3732,$B$13,Zepto_Data!$M$2:$M$3732,$B$14),IF($B$6="Sum",SUMIFS(INDEX(ZPD,0,$B$5),INDEX(ZPD,0,$B$3),$B39,INDEX(ZPD,0,$B$8),J$18,Zepto_Data!$A$2:$A$3732,$B$11,Zepto_Data!$L$2:$L$3732,$B$12,Zepto_Data!$K$2:$K$3732,$B$13,Zepto_Data!$M$2:$M$3732,$B$14),IFERROR(SUMIFS(INDEX(ZPD,0,$B$5),INDEX(ZPD,0,$B$3),$B39,INDEX(ZPD,0,$B$8),J$18,Zepto_Data!$A$2:$A$3732,$B$11,Zepto_Data!$L$2:$L$3732,$B$12,Zepto_Data!$K$2:$K$3732,$B$13,Zepto_Data!$M$2:$M$3732,$B$14)/COUNTIFS(INDEX(ZPD,0,$B$3),$B39,INDEX(ZPD,0,$B$8),J$18,Zepto_Data!$A$2:$A$3732,$B$11,Zepto_Data!$L$2:$L$3732,$B$12,Zepto_Data!$K$2:$K$3732,$B$13,Zepto_Data!$M$2:$M$3732,$B$14),0))))
A44: k | B44: pos | C44: label | D44: value | E44: share | F44: =F19 -> All | G44: =G19 | H44: =H19 | I44: =I19 | J44: =J19
A45: 1 | B45: =IFERROR(MATCH(A45,$D$20:$D$39,0),0) -> 4 | C45: =IF(OR(A45>$B$9,B45=0),"",INDEX($B$20:$B$39,B45)) -> Cooking Essentials | D45: =IF(C45="","",INDEX($C$20:$C$39,B45)) -> 337369 | E45: =IF(OR(C45="",$B$6="Average"),"",D45/SUM($C$20:$C$39)) -> 0.15040431 | F45: =IF(OR($C45="",F$19=""),"",INDEX(F$20:F$39,$B45)) -> 337369 | G45: =IF(OR($C45="",G$19=""),"",INDEX(G$20:G$39,$B45)) | H45: =IF(OR($C45="",H$19=""),"",INDEX(H$20:H$39,$B45)) | I45: =IF(OR($C45="",I$19=""),"",INDEX(I$20:I$39,$B45)) | J45: =IF(OR($C45="",J$19=""),"",INDEX(J$20:J$39,$B45))
A46: 2 | B46: =IFERROR(MATCH(A46,$D$20:$D$39,0),0) -> 11 | C46: =IF(OR(A46>$B$9,B46=0),"",INDEX($B$20:$B$39,B46)) -> Munchies | D46: =IF(C46="","",INDEX($C$20:$C$39,B46)) -> 337369 | E46: =IF(OR(C46="",$B$6="Average"),"",D46/SUM($C$20:$C$39)) -> 0.15040431 | F46: =IF(OR($C46="",F$19=""),"",INDEX(F$20:F$39,$B46)) -> 337369 | G46: =IF(OR($C46="",G$19=""),"",INDEX(G$20:G$39,$B46)) | H46: =IF(OR($C46="",H$19=""),"",INDEX(H$20:H$39,$B46)) | I46: =IF(OR($C46="",I$19=""),"",INDEX(I$20:I$39,$B46)) | J46: =IF(OR($C46="",J$19=""),"",INDEX(J$20:J$39,$B46))
A47: 3 | B47: =IFERROR(MATCH(A47,$D$20:$D$39,0),0) -> 12 | C47: =IF(OR(A47>$B$9,B47=0),"",INDEX($B$20:$B$39,B47)) -> Paan Corner | D47: =IF(C47="","",INDEX($C$20:$C$39,B47)) -> 270849 | E47: =IF(OR(C47="",$B$6="Average"),"",D47/SUM($C$20:$C$39)) -> 0.12074867 | F47: =IF(OR($C47="",F$19=""),"",INDEX(F$20:F$39,$B47)) -> 270849 | G47: =IF(OR($C47="",G$19=""),"",INDEX(G$20:G$39,$B47)) | H47: =IF(OR($C47="",H$19=""),"",INDEX(H$20:H$39,$B47)) | I47: =IF(OR($C47="",I$19=""),"",INDEX(I$20:I$39,$B47)) | J47: =IF(OR($C47="",J$19=""),"",INDEX(J$20:J$39,$B47))
A48: 4 | B48: =IFERROR(MATCH(A48,$D$20:$D$39,0),0) -> 14 | C48: =IF(OR(A48>$B$9,B48=0),"",INDEX($B$20:$B$39,B48)) -> Personal Care | D48: =IF(C48="","",INDEX($C$20:$C$39,B48)) -> 270849 | E48: =IF(OR(C48="",$B$6="Average"),"",D48/SUM($C$20:$C$39)) -> 0.12074867 | F48: =IF(OR($C48="",F$19=""),"",INDEX(F$20:F$39,$B48)) -> 270849 | G48: =IF(OR($C48="",G$19=""),"",INDEX(G$20:G$39,$B48)) | H48: =IF(OR($C48="",H$19=""),"",INDEX(H$20:H$39,$B48)) | I48: =IF(OR($C48="",I$19=""),"",INDEX(I$20:I$39,$B48)) | J48: =IF(OR($C48="",J$19=""),"",INDEX(J$20:J$39,$B48))
A49: 5 | B49: =IFERROR(MATCH(A49,$D$20:$D$39,0),0) -> 3 | C49: =IF(OR(A49>$B$9,B49=0),"",INDEX($B$20:$B$39,B49)) -> Chocolates & Candies | D49: =IF(C49="","",INDEX($C$20:$C$39,B49)) -> 224385 | E49: =IF(OR(C49="",$B$6="Average"),"",D49/SUM($C$20:$C$39)) -> 0.1000343 | F49: =IF(OR($C49="",F$19=""),"",INDEX(F$20:F$39,$B49)) -> 224385 | G49: =IF(OR($C49="",G$19=""),"",INDEX(G$20:G$39,$B49)) | H49: =IF(OR($C49="",H$19=""),"",INDEX(H$20:H$39,$B49)) | I49: =IF(OR($C49="",I$19=""),"",INDEX(I$20:I$39,$B49)) | J49: =IF(OR($C49="",J$19=""),"",INDEX(J$20:J$39,$B49))
A50: 6 | B50: =IFERROR(MATCH(A50,$D$20:$D$39,0),0) -> 9 | C50: =IF(OR(A50>$B$9,B50=0),"",INDEX($B$20:$B$39,B50)) -> Ice Cream & Desserts | D50: =IF(C50="","",INDEX($C$20:$C$39,B50)) -> 224385 | E50: =IF(OR(C50="",$B$6="Average"),"",D50/SUM($C$20:$C$39)) -> 0.1000343 | F50: =IF(OR($C50="",F$19=""),"",INDEX(F$20:F$39,$B50)) -> 224385 | G50: =IF(OR($C50="",G$19=""),"",INDEX(G$20:G$39,$B50)) | H50: =IF(OR($C50="",H$19=""),"",INDEX(H$20:H$39,$B50)) | I50: =IF(OR($C50="",I$19=""),"",INDEX(I$20:I$39,$B50)) | J50: =IF(OR($C50="",J$19=""),"",INDEX(J$20:J$39,$B50))
A51: 7 | B51: =IFERROR(MATCH(A51,$D$20:$D$39,0),0) -> 13 | C51: =IF(OR(A51>$B$9,B51=0),"",INDEX($B$20:$B$39,B51)) -> Packaged Food | D51: =IF(C51="","",INDEX($C$20:$C$39,B51)) -> 224385 | E51: =IF(OR(C51="",$B$6="Average"),"",D51/SUM($C$20:$C$39)) -> 0.1000343 | F51: =IF(OR($C51="",F$19=""),"",INDEX(F$20:F$39,$B51)) -> 224385 | G51: =IF(OR($C51="",G$19=""),"",INDEX(G$20:G$39,$B51)) | H51: =IF(OR($C51="",H$19=""),"",INDEX(H$20:H$39,$B51)) | I51: =IF(OR($C51="",I$19=""),"",INDEX(I$20:I$39,$B51)) | J51: =IF(OR($C51="",J$19=""),"",INDEX(J$20:J$39,$B51))
A52: 8 | B52: =IFERROR(MATCH(A52,$D$20:$D$39,0),0) -> 8 | C52: =IF(OR(A52>$B$9,B52=0),"",INDEX($B$20:$B$39,B52)) -> Home & Cleaning | D52: =IF(C52="","",INDEX($C$20:$C$39,B52)) -> 122661 | E52: =IF(OR(C52="",$B$6="Average"),"",D52/SUM($C$20:$C$39)) -> 0.05468417 | F52: =IF(OR($C52="",F$19=""),"",INDEX(F$20:F$39,$B52)) -> 122661 | G52: =IF(OR($C52="",G$19=""),"",INDEX(G$20:G$39,$B52)) | H52: =IF(OR($C52="",H$19=""),"",INDEX(H$20:H$39,$B52)) | I52: =IF(OR($C52="",I$19=""),"",INDEX(I$20:I$39,$B52)) | J52: =IF(OR($C52="",J$19=""),"",INDEX(J$20:J$39,$B52))
A53: 9 | B53: =IFERROR(MATCH(A53,$D$20:$D$39,0),0) -> 7 | C53: =IF(OR(A53>$B$9,B53=0),"",INDEX($B$20:$B$39,B53)) -> Health & Hygiene | D53: =IF(C53="","",INDEX($C$20:$C$39,B53)) -> 64180 | E53: =IF(OR(C53="",$B$6="Average"),"",D53/SUM($C$20:$C$39)) -> 0.028612436 | F53: =IF(OR($C53="",F$19=""),"",INDEX(F$20:F$39,$B53)) -> 64180 | G53: =IF(OR($C53="",G$19=""),"",INDEX(G$20:G$39,$B53)) | H53: =IF(OR($C53="",H$19=""),"",INDEX(H$20:H$39,$B53)) | I53: =IF(OR($C53="",I$19=""),"",INDEX(I$20:I$39,$B53)) | J53: =IF(OR($C53="",J$19=""),"",INDEX(J$20:J$39,$B53))
A54: 10 | B54: =IFERROR(MATCH(A54,$D$20:$D$39,0),0) -> 1 | C54: =IF(OR(A54>$B$9,B54=0),"",INDEX($B$20:$B$39,B54)) -> Beverages | D54: =IF(C54="","",INDEX($C$20:$C$39,B54)) -> 55051 | E54: =IF(OR(C54="",$B$6="Average"),"",D54/SUM($C$20:$C$39)) -> 0.024542587 | F54: =IF(OR($C54="",F$19=""),"",INDEX(F$20:F$39,$B54)) -> 55051 | G54: =IF(OR($C54="",G$19=""),"",INDEX(G$20:G$39,$B54)) | H54: =IF(OR($C54="",H$19=""),"",INDEX(H$20:H$39,$B54)) | I54: =IF(OR($C54="",I$19=""),"",INDEX(I$20:I$39,$B54)) | J54: =IF(OR($C54="",J$19=""),"",INDEX(J$20:J$39,$B54))
A55: 11 | B55: =IFERROR(MATCH(A55,$D$20:$D$39,0),0) -> 5 | C55: =IF(OR(A55>$B$9,B55=0),"",INDEX($B$20:$B$39,B55)) -> Dairy, Bread & Batter | D55: =IF(C55="","",INDEX($C$20:$C$39,B55)) -> 55051 | E55: =IF(OR(C55="",$B$6="Average"),"",D55/SUM($C$20:$C$39)) -> 0.024542587 | F55: =IF(OR($C55="",F$19=""),"",INDEX(F$20:F$39,$B55)) -> 55051 | G55: =IF(OR($C55="",G$19=""),"",INDEX(G$20:G$39,$B55)) | H55: =IF(OR($C55="",H$19=""),"",INDEX(H$20:H$39,$B55)) | I55: =IF(OR($C55="",I$19=""),"",INDEX(I$20:I$39,$B55)) | J55: =IF(OR($C55="",J$19=""),"",INDEX(J$20:J$39,$B55))
A56: 12 | B56: =IFERROR(MATCH(A56,$D$20:$D$39,0),0) -> 2 | C56: =IF(OR(A56>$B$9,B56=0),"",INDEX($B$20:$B$39,B56)) -> Biscuits | D56: =IF(C56="","",INDEX($C$20:$C$39,B56)) -> 25007.6 | E56: =IF(OR(C56="",$B$6="Average"),"",D56/SUM($C$20:$C$39)) -> 0.011148775 | F56: =IF(OR($C56="",F$19=""),"",INDEX(F$20:F$39,$B56)) -> 25007.6 | G56: =IF(OR($C56="",G$19=""),"",INDEX(G$20:G$39,$B56)) | H56: =IF(OR($C56="",H$19=""),"",INDEX(H$20:H$39,$B56)) | I56: =IF(OR($C56="",I$19=""),"",INDEX(I$20:I$39,$B56)) | J56: =IF(OR($C56="",J$19=""),"",INDEX(J$20:J$39,$B56))
A59: stock status | B59: SKUs
A60: In stock | B60: =COUNTIFS(Zepto_Data!$L$2:$L$3732,A60,Zepto_Data!$A$2:$A$3732,$B$11,Zepto_Data!$L$2:$L$3732,$B$12,Zepto_Data!$K$2:$K$3732,$B$13,Zepto_Data!$M$2:$M$3732,$B$14) -> 3278
A61: Out of stock | B61: =COUNTIFS(Zepto_Data!$L$2:$L$3732,A61,Zepto_Data!$A$2:$A$3732,$B$11,Zepto_Data!$L$2:$L$3732,$B$12,Zepto_Data!$K$2:$K$3732,$B$13,Zepto_Data!$M$2:$M$3732,$B$14) -> 453

Sheet ZP_Lists
A1: Dimension | B1: Data column # | D1: Value field | E1: Data column # | G1: Aggregation | H1: Sort | I1: Top N | J1: Split by | L1: Category | M1: Product (top 20 by revenue) | N1: Weight category | O1: Stock status | P1: Discount band | Q1: Price band | S1: Category options | T1: Stock status options | U1: Weight category options | V1: Discount band options
A2: Category | B2: 1 | D2: Revenue (Rs) | E2: 10 | G2: Sum | H2: Value: high to low | I2: 5 | J2: None | L2: Beverages | M2: Borges Extra Light Olive Oil Bottle | N2: 1-Low | O2: In stock | P2: 1) Under 5% | Q2: 1) Under Rs 50 | S2: All | T2: All | U2: All | V2: All
A3: Product (top 20 by revenue) | B3: 2 | D3: MRP (Rs) | E3: 3 | G3: Average | H3: Value: low to high | I3: 8 | J3: Stock status | L3: Biscuits | M3: Dhara Filtered Groundnut Oil (Jar) | N3: 2-Medium | O3: Out of stock | P3: 2) 5-9% | Q3: 2) Rs 50-99 | S3: Beverages | T3: In stock | U3: 1-Low | V3: 1) Under 5%
A4: Weight category | B4: 11 | D4: Discount % | E4: 4 | G4: Count | H4: Natural order | I4: 10 | J4: Weight category | L4: Chocolates & Candies | M4: Praakritik Natural Desi Gir Cow A2 Ghee | N4: 3-Bulk | P4: 3) 10-14% | Q4: 3) Rs 100-199 | S4: Biscuits | T4: Out of stock | U4: 2-Medium | V4: 2) 5-9%
A5: Stock status | B5: 12 | D5: Available quantity | E5: 5 | I5: 12 | J5: Discount band | L5: Cooking Essentials | M5: Saffola Gold (Jar) | P5: 4) 15-24% | Q5: 4) Rs 200-499 | S5: Chocolates & Candies | U5: 3-Bulk | V5: 3) 10-14%
A6: Discount band | B6: 13 | D6: Selling price (Rs) | E6: 6 | J6: Price band | L6: Dairy, Bread & Batter | M6: Dhara Kachi Ghani Mustard Oil Jar | P6: 5) 25%+ | Q6: 5) Rs 500+ | S6: Cooking Essentials | V6: 4) 15-24%
A7: Price band | B7: 14 | D7: Weight (g) | E7: 7 | L7: Fruits & Vegetables | M7: Fortune Rice Bran Health Oil (Jar) | S7: Dairy, Bread & Batter | V7: 5) 25%+
D8: Inventory weight (kg) | E8: 15 | L8: Health & Hygiene | M8: Fortune Soyabean Oil | S8: Fruits & Vegetables
L9: Home & Cleaning | M9: Dhara Health Refined Sun Flower Oil Jar | S9: Health & Hygiene
L10: Ice Cream & Desserts | M10: Nestle Nestle Nan Pro Follow-Up Formula | S10: Home & Cleaning
L11: Meats, Fish & Eggs | M11: Fortune Sunlite Refined Sunflower (Jar) | S11: Ice Cream & Desserts
L12: Munchies | M12: Pampers Premium Care Pants - Medium | S12: Meats, Fish & Eggs
L13: Paan Corner | M13: Kellogg's Real Almond & Honey Corn Flakes | S13: Munchies
L14: Packaged Food | M14: Godrej Yummiez Chicken Punjabi Tikka | S14: Paan Corner
L15: Personal Care | M15: Sunsilk Lusciously Thick & Long Shampoo | S15: Packaged Food
M16: Bagrry's Fruit Fibre Muesli Mixed Fruit | S16: Personal Care
M17: Popular Essentials Californian Almond
M18: Kellogg's Original Corn Flakes
M19: Pedigree Puppy Dry Dog Food Food Chicken & Milk
M20: Kellogg’s Chocos Protein And Fibre Of 1 Roti
M21: Japanese Choice Udon Noodles

Sheet Zepto_Data
A1: Category | B1: name | C1: mrp | D1: discountPercent | E1: availableQuantity | F1: discountedSellingPrice | G1: weightInGms | H1: outOfStock | I1: quantity | J1: Revenue (Rs) | K1: Weight_Category | L1: Stock_Status | M1: Discount_Band | N1: Price_Band | O1: Inventory_Weight_kg
A2: Fruits & Vegetables | B2: Onion | C2: 25 | D2: 16 | E2: 3 | F2: 21 | G2: 1000 | H2: FALSE | I2: 1 | J2: =F2*E2 -> 63 | K2: =IF(G2<1000,"1-Low",IF(G2<5000,"2-Medium","3-Bulk")) -> 2-Medium | L2: =IF(H2="TRUE","Out of stock","In stock") -> In stock | M2: =IF(D2<5,"1) Under 5%",IF(D2<10,"2) 5-9%",IF(D2<15,"3) 10-14%",IF(D2<25,"4) 15-24%","5) 25%+")))) -> 4) 15-24% | N2: =IF(F2<50,"1) Under Rs 50",IF(F2<100,"2) Rs 50-99",IF(F2<200,"3) Rs 100-199",IF(F2<500,"4) Rs 200-499","5) Rs 500+")))) -> 1) Under Rs 50 | O2: =G2*E2/1000 -> 3
A3: Fruits & Vegetables | B3: Tomato Hybrid | C3: 42 | D3: 16 | E3: 3 | F3: 35 | G3: 1000 | H3: FALSE | I3: 1 | J3: =F3*E3 -> 105 | K3: =IF(G3<1000,"1-Low",IF(G3<5000,"2-Medium","3-Bulk")) -> 2-Medium | L3: =IF(H3="TRUE","Out of stock","In stock") -> In stock | M3: =IF(D3<5,"1) Under 5%",IF(D3<10,"2) 5-9%",IF(D3<15,"3) 10-14%",IF(D3<25,"4) 15-24%","5) 25%+")))) -> 4) 15-24% | N3: =IF(F3<50,"1) Under Rs 50",IF(F3<100,"2) Rs 50-99",IF(F3<200,"3) Rs 100-199",IF(F3<500,"4) Rs 200-499","5) Rs 500+")))) -> 1) Under Rs 50 | O3: =G3*E3/1000 -> 3
A4: Fruits & Vegetables | B4: Tender Coconut | C4: 51 | D4: 15 | E4: 3 | F4: 43 | G4: 58 | H4: FALSE | I4: 1 | J4: =F4*E4 -> 129 | K4: =IF(G4<1000,"1-Low",IF(G4<5000,"2-Medium","3-Bulk")) -> 1-Low | L4: =IF(H4="TRUE","Out of stock","In stock") -> In stock | M4: =IF(D4<5,"1) Under 5%",IF(D4<10,"2) 5-9%",IF(D4<15,"3) 10-14%",IF(D4<25,"4) 15-24%","5) 25%+")))) -> 4) 15-24% | N4: =IF(F4<50,"1) Under Rs 50",IF(F4<100,"2) Rs 50-99",IF(F4<200,"3) Rs 100-199",IF(F4<500,"4) Rs 200-499","5) Rs 500+")))) -> 1) Under Rs 50 | O4: =G4*E4/1000 -> 0.174
A5: Fruits & Vegetables | B5: Coriander Leaves | C5: 20 | D5: 15 | E5: 3 | F5: 17 | G5: 100 | H5: FALSE | I5: 100 | J5: =F5*E5 -> 51 | K5: =IF(G5<1000,"1-Low",IF(G5<5000,"2-Medium","3-Bulk")) -> 1-Low | L5: =IF(H5="TRUE","Out of stock","In stock") -> In stock | M5: =IF(D5<5,"1) Under 5%",IF(D5<10,"2) 5-9%",IF(D5<15,"3) 10-14%",IF(D5<25,"4) 15-24%","5) 25%+")))) -> 4) 15-24% | N5: =IF(F5<50,"1) Under Rs 50",IF(F5<100,"2) Rs 50-99",IF(F5<200,"3) Rs 100-199",IF(F5<500,"4) Rs 200-499","5) Rs 500+")))) -> 1) Under Rs 50 | O5: =G5*E5/1000 -> 0.3
A6: Fruits & Vegetables | B6: Ladies Finger | C6: 14 | D6: 14 | E6: 3 | F6: 12 | G6: 250 | H6: FALSE | I6: 250 | J6: =F6*E6 -> 36 | K6: =IF(G6<1000,"1-Low",IF(G6<5000,"2-Medium","3-Bulk")) -> 1-Low | L6: =IF(H6="TRUE","Out of stock","In stock") -> In stock | M6: =IF(D6<5,"1) Under 5%",IF(D6<10,"2) 5-9%",IF(D6<15,"3) 10-14%",IF(D6<25,"4) 15-24%","5) 25%+")))) -> 3) 10-14% | N6: =IF(F6<50,"1) Under Rs 50",IF(F6<100,"2) Rs 50-99",IF(F6<200,"3) Rs 100-199",IF(F6<500,"4) Rs 200-499","5) Rs 500+")))) -> 1) Under Rs 50 | O6: =G6*E6/1000 -> 0.75
A7: Fruits & Vegetables | B7: Potato | C7: 35 | D7: 17 | E7: 3 | F7: 29 | G7: 1000 | H7: FALSE | I7: 1 | J7: =F7*E7 -> 87 | K7: =IF(G7<1000,"1-Low",IF(G7<5000,"2-Medium","3-Bulk")) -> 2-Medium | L7: =IF(H7="TRUE","Out of stock","In stock") -> In stock | M7: =IF(D7<5,"1) Under 5%",IF(D7<10,"2) 5-9%",IF(D7<15,"3) 10-14%",IF(D7<25,"4) 15-24%","5) 25%+")))) -> 4) 15-24% | N7: =IF(F7<50,"1) Under Rs 50",IF(F7<100,"2) Rs 50-99",IF(F7<200,"3) Rs 100-199",IF(F7<500,"4) Rs 200-499","5) Rs 500+")))) -> 1) Under Rs 50 | O7: =G7*E7/1000 -> 3
A8: Fruits & Vegetables | B8: Lemon | C8: 75 | D8: 16 | E8: 3 | F8: 63 | G8: 200 | H8: FALSE | I8: 200 | J8: =F8*E8 -> 189 | K8: =IF(G8<1000,"1-Low",IF(G8<5000,"2-Medium","3-Bulk")) -> 1-Low | L8: =IF(H8="TRUE","Out of stock","In stock") -> In stock | M8: =IF(D8<5,"1) Under 5%",IF(D8<10,"2) 5-9%",IF(D8<15,"3) 10-14%",IF(D8<25,"4) 15-24%","5) 25%+")))) -> 4) 15-24% | N8: =IF(F8<50,"1) Under Rs 50",IF(F8<100,"2) Rs 50-99",IF(F8<200,"3) Rs 100-199",IF(F8<500,"4) Rs 200-499","5) Rs 500+")))) -> 2) Rs 50-99 | O8: =G8*E8/1000 -> 0.6
A9: Fruits & Vegetables | B9: Watermelon | C9: 58 | D9: 15 | E9: 3 | F9: 49 | G9: 58 | H9: FALSE | I9: 1 | J9: =F9*E9 -> 147 | K9: =IF(G9<1000,"1-Low",IF(G9<5000,"2-Medium","3-Bulk")) -> 1-Low | L9: =IF(H9="TRUE","Out of stock","In stock") -> In stock | M9: =IF(D9<5,"1) Under 5%",IF(D9<10,"2) 5-9%",IF(D9<15,"3) 10-14%",IF(D9<25,"4) 15-24%","5) 25%+")))) -> 4) 15-24% | N9: =IF(F9<50,"1) Under Rs 50",IF(F9<100,"2) Rs 50-99",IF(F9<200,"3) Rs 100-199",IF(F9<500,"4) Rs 200-499","5) Rs 500+")))) -> 1) Under Rs 50 | O9: =G9*E9/1000 -> 0.174
A10: Fruits & Vegetables | B10: Capsicum Green | C10: 23 | D10: 17 | E10: 3 | F10: 19 | G10: 250 | H10: FALSE | I10: 250 | J10: =F10*E10 -> 57 | K10: =IF(G10<1000,"1-Low",IF(G10<5000,"2-Medium","3-Bulk")) -> 1-Low | L10: =IF(H10="TRUE","Out of stock","In stock") -> In stock | M10: =IF(D10<5,"1) Under 5%",IF(D10<10,"2) 5-9%",IF(D10<15,"3) 10-14%",IF(D10<25,"4) 15-24%","5) 25%+")))) -> 4) 15-24% | N10: =IF(F10<50,"1) Under Rs 50",IF(F10<100,"2) Rs 50-99",IF(F10<200,"3) Rs 100-199",IF(F10<500,"4) Rs 200-499","5) Rs 500+")))) -> 1) Under Rs 50 | O10: =G10*E10/1000 -> 0.75
A11: Fruits & Vegetables | B11: Chilli Green | C11: 19 | D11: 15 | E11: 3 | F11: 16 | G11: 100 | H11: FALSE | I11: 100 | J11: =F11*E11 -> 48 | K11: =IF(G11<1000,"1-Low",IF(G11<5000,"2-Medium","3-Bulk")) -> 1-Low | L11: =IF(H11="TRUE","Out of stock","In stock") -> In stock | M11: =IF(D11<5,"1) Under 5%",IF(D11<10,"2) 5-9%",IF(D11<15,"3) 10-14%",IF(D11<25,"4) 15-24%","5) 25%+")))) -> 4) 15-24% | N11: =IF(F11<50,"1) Under Rs 50",IF(F11<100,"2) Rs 50-99",IF(F11<200,"3) Rs 100-199",IF(F11<500,"4) Rs 200-499","5) Rs 500+")))) -> 1) Under Rs 50 | O11: =G11*E11/1000 -> 0.3
A12: Fruits & Vegetables | B12: Banana Robusta | C12: 29 | D12: 17 | E12: 3 | F12: 24 | G12: 348 | H12: FALSE | I12: 6 | J12: =F12*E12 -> 72 | K12: =IF(G12<1000,"1-Low",IF(G12<5000,"2-Medium","3-Bulk")) -> 1-Low | L12: =IF(H12="TRUE","Out of stock","In stock") -> In stock | M12: =IF(D12<5,"1) Under 5%",IF(D12<10,"2) 5-9%",IF(D12<15,"3) 10-14%",IF(D12<25,"4) 15-24%","5) 25%+")))) -> 4) 15-24% | N12: =IF(F12<50,"1) Under Rs 50",IF(F12<100,"2) Rs 50-99",IF(F12<200,"3) Rs 100-199",IF(F12<500,"4) Rs 200-499","5) Rs 500+")))) -> 1) Under Rs 50 | O12: =G12*E12/1000 -> 1.044
A13: Fruits & Vegetables | B13: Garlic Indian | C13: 11 | D13: 18 | E13: 3 | F13: 9 | G13: 100 | H13: FALSE | I13: 100 | J13: =F13*E13 -> 27 | K13: =IF(G13<1000,"1-Low",IF(G13<5000,"2-Medium","3-Bulk")) -> 1-Low | L13: =IF(H13="TRUE","Out of stock","In stock") -> In stock | M13: =IF(D13<5,"1) Under 5%",IF(D13<10,"2) 5-9%",IF(D13<15,"3) 10-14%",IF(D13<25,"4) 15-24%","5) 25%+")))) -> 4) 15-24% | N13: =IF(F13<50,"1) Under Rs 50",IF(F13<100,"2) Rs 50-99",IF(F13<200,"3) Rs 100-199",IF(F13<500,"4) Rs 200-499","5) Rs 500+")))) -> 1) Under Rs 50 | O13: =G13*E13/1000 -> 0.3
... A3732: Health & Hygiene | B3732: Dettol Antiseptic Liquid | C3732: 30 | D3732: 0 | E3732: 0 | F3732: 30 | G3732: 60 | H3732: TRUE | I3732: 60 | J3732: =F3732*E3732 -> 0 | K3732: =IF(G3732<1000,"1-Low",IF(G3732<5000,"2-Medium","3-Bulk")) -> 1-Low | L3732: =IF(H3732="TRUE","Out of stock","In stock") -> Out of stock | M3732: =IF(D3732<5,"1) Under 5%",IF(D3732<10,"2) 5-9%",IF(D3732<15,"3) 10-14%",IF(D3732<25,"4) 15-24%","5) 25%+")))) -> 1) Under 5% | N3732: =IF(F3732<50,"1) Under Rs 50",IF(F3732<100,"2) Rs 50-99",IF(F3732<200,"3) Rs 100-199",IF(F3732<500,"4) Rs 200-499","5) Rs 500+")))) -> 1) Under Rs 50 | O3732: =G3732*E3732/1000 -> 0

Sheet ZP_Pivots
A1: Pivot tables behind the slicer dashboard. They refresh when the file opens in Excel; do not move or delete them.
A3: Stock_Status | B3: (All)
A4: Weight_Category | B4: (All)
A5: Discount_Band | B5: (All)
A7: Row Labels | B7: Total Revenue (Rs) | C7: Average Discount %
A8: Beverages | B8: 55051 | C8: 7.1550388
A9: Biscuits | B9: 25007.6 | C9: 8.244898
A10: Chocolates & Candies | B10: 224385 | C10: 8.3247423
A11: Cooking Essentials | B11: 337369 | C11: 7.1634241
A12: Dairy, Bread & Batter | B12: 55051 | C12: 7.1550388
A13: Fruits & Vegetables | B13: 10846 | C13: 15.462366
A14: Health & Hygiene | B14: 64180 | C14: 8.0515464
A15: Home & Cleaning | B15: 122661 | C15: 5.7046632
A16: Ice Cream & Desserts | B16: 224385 | C16: 8.3247423
A17: Meats, Fish & Eggs | B17: 20693 | C17: 11.031746
A18: Munchies | B18: 337369 | C18: 7.1634241
A19: Paan Corner | B19: 270849 | C19: 6.25
... A22: Grand Total | B22: 2243080.6 | C22: 7.619137
A25: Category | B25: (All)
A26: Weight_Category | B26: (All)
A27: Discount_Band | B27: (All)
A29: Row Labels | B29: SKUs
A30: In stock | B30: 3278
A31: Out of stock | B31: 453
A32: Grand Total | B32: 3731
A35: Category | B35: (All)
A36: Stock_Status | B36: (All)
A37: Discount_Band | B37: (All)
A39: Row Labels | B39: Inventory Weight (kg)
A40: 1-Low | B40: 3359.749
A41: 2-Medium | B41: 1346.1
A42: 3-Bulk | B42: 1300
A43: Grand Total | B43: 6005.849
A46: Category | B46: (All)
A47: Stock_Status | B47: (All)
A48: Weight_Category | B48: (All)
A50: Row Labels | B50: SKUs
A51: 1) Under 5% | B51: 1615
A52: 2) 5-9% | B52: 836
A53: 3) 10-14% | B53: 680
A54: 4) 15-24% | B54: 394
A55: 5) 25%+ | B55: 206
A56: Grand Total | B56: 3731
